<?xml version="1.0"?>
<opencv_storage>
<calibration_time>"ven 09 dic 2016 17:50:03 CET"</calibration_time>
<nr_of_frames>25</nr_of_frames>
<image_width>640</image_width>
<image_height>480</image_height>
<board_width>9</board_width>
<board_height>6</board_height>
<square_size>12.</square_size>
<fix_aspect_ratio>1.</fix_aspect_ratio>
<!-- flags: +fix_aspectRatio +fix_principal_point +zero_tangent_dist -->
<flags>6158</flags>
<fisheye_model>0</fisheye_model>
<camera_matrix type_id="opencv-matrix">
  <rows>3</rows>
  <cols>3</cols>
  <dt>d</dt>
  <data>
    1.1029306292014924e+03 0. 3.1950000000000000e+02 0.
    1.1029306292014924e+03 2.3950000000000000e+02 0. 0. 1.</data></camera_matrix>
<distortion_coefficients type_id="opencv-matrix">
  <rows>5</rows>
  <cols>1</cols>
  <dt>d</dt>
  <data>
    -3.0077359914194270e-02 -3.3506088885837393e+01 0. 0.
    6.6507700407386619e+02</data></distortion_coefficients>
<avg_reprojection_error>1.2641121054748669e-01</avg_reprojection_error>
<per_view_reprojection_errors type_id="opencv-matrix">
  <rows>25</rows>
  <cols>1</cols>
  <dt>f</dt>
  <data>
    1.52388930e-01 1.86483234e-01 1.40678078e-01 1.51519224e-01
    1.42898947e-01 1.47442356e-01 1.55066192e-01 1.21508390e-01
    1.29500806e-01 1.07419461e-01 1.08368225e-01 1.12837985e-01
    9.98924077e-02 1.10405348e-01 1.24053910e-01 1.18414544e-01
    9.91234779e-02 1.06529295e-01 1.14213370e-01 1.17386095e-01
    1.18598066e-01 1.16434008e-01 1.04926258e-01 1.13847166e-01
    1.17571212e-01</data></per_view_reprojection_errors>
<extrinsic_parameters type_id="opencv-matrix">
  <rows>25</rows>
  <cols>6</cols>
  <dt>d</dt>
  <data>
    6.5605281360190421e-02 7.3992101243027561e-02 3.0222851319890989e+00
    2.1142898801833169e+01 2.2642790316005922e+01 5.3778706261954846e+02
    5.9338909697453812e-02 9.7553724315587551e-02 3.0211394004120540e+00
    2.1557849374430738e+01 2.0811458069092751e+01 5.4268895019938077e+02
    8.0086831739448056e-02 8.7391165294400275e-02 3.0220488828087344e+00
    2.1848696104189273e+01 1.9620145237999012e+01 5.4315522631767590e+02
    7.9620911463252161e-02 7.3948385622318369e-02 3.0231024369489394e+00
    2.2457275352010605e+01 2.0338733829773243e+01 5.4531000115614654e+02
    8.7241071243620655e-02 1.0021782073398651e-01 3.0300372313163346e+00
    2.2413697053371919e+01 2.1810192016313891e+01 5.4399130944485034e+02
    8.6420730196762385e-02 8.7588854487554518e-02 3.0364640657343460e+00
    2.2646086227384767e+01 2.2710696720199007e+01 5.3997413248703094e+02
    8.3543578250215342e-02 1.3458759253049077e-01 3.0558381101327110e+00
    2.4829412616896896e+01 2.2897239315927983e+01 5.4134037836321772e+02
    9.0986188410028659e-02 1.4913746203995160e-01 3.0655187530679844e+00
    2.7130306400522155e+01 2.2031858700424380e+01 5.4153566523190432e+02
    8.6752883605443296e-02 1.7000020197556376e-01 3.0662564057735677e+00
    2.7676276404692405e+01 2.0171732329470650e+01 5.4141555412071875e+02
    9.2778108547622862e-02 1.6964286141024049e-01 3.0648505419715408e+00
    2.8094283084686491e+01 1.7944022820767259e+01 5.4189899215882190e+02
    9.0842322725092239e-02 1.7360705202828031e-01 3.0645166572255507e+00
    2.7653401593956719e+01 1.6868662139500245e+01 5.4148207583335613e+02
    9.8871629434710576e-02 1.7224384645956856e-01 3.0631701037662840e+00
    2.7830938142908995e+01 1.5104523876487557e+01 5.4130422624482549e+02
    1.0072471943377159e-01 1.6976249102569488e-01 3.0637570524938003e+00
    2.7209427224950122e+01 1.5786685788208855e+01 5.4021862288552165e+02
    1.0941719187364721e-01 1.6576461081189892e-01 3.0625130248534904e+00
    2.6655579195056553e+01 1.5631930685536233e+01 5.3948871680007642e+02
    1.0677612858706044e-01 1.7411118440761500e-01 3.0633992636380487e+00
    2.6465204411729239e+01 1.4940217376371479e+01 5.4015568714050141e+02
    1.0571211173385890e-01 1.7118375573391156e-01 3.0627703897016705e+00
    2.7176127826396591e+01 1.3405482199394806e+01 5.4171139564597365e+02
    1.0423463615958900e-01 1.7102612790537894e-01 3.0646191267087106e+00
    2.7472794926019699e+01 1.3895256421623806e+01 5.4137269456351271e+02
    1.1216985721942567e-01 1.6557160213884667e-01 3.0612940751814146e+00
    2.7596272249252522e+01 1.2330095718190684e+01 5.4155811803598351e+02
    1.1669580136455372e-01 1.6843798863796700e-01 3.0615307437476784e+00
    2.7765783362885163e+01 1.2576641161914608e+01 5.4100568200987323e+02
    1.2134142879499298e-01 1.7808229433389100e-01 3.0635085426473916e+00
    2.7640529387099072e+01 1.2540600108004536e+01 5.4030633327265730e+02
    1.1950033048195931e-01 1.7395519514884045e-01 3.0620593219758176e+00
    2.7704911124620423e+01 1.1690040119712108e+01 5.4004988766263557e+02
    1.1792912954991731e-01 1.7554564014246740e-01 3.0612199028285985e+00
    2.7839050090658674e+01 1.1210009032503697e+01 5.4060186726736345e+02
    1.1450891022770028e-01 1.7326996920073737e-01 3.0611474170486201e+00
    2.7486711194194477e+01 1.1033165907154570e+01 5.4094846326485424e+02
    1.1498473822218382e-01 1.6783186493896327e-01 3.0609146966653480e+00
    2.7624571698457824e+01 1.1293819343029918e+01 5.4205754509538065e+02
    1.0915957151065989e-01 1.7762691319940646e-01 3.0596947050166445e+00
    2.7973991870866257e+01 1.0795220793836004e+01 5.4315382225659903e+02</data></extrinsic_parameters>
<image_points type_id="opencv-matrix">
  <rows>25</rows>
  <cols>54</cols>
  <dt>"2f"</dt>
  <data>
    3.62901733e+02 2.85752228e+02 3.38464752e+02 2.88654541e+02
    3.14034515e+02 2.91570679e+02 2.89536713e+02 2.94445282e+02
    2.65431458e+02 2.97156952e+02 2.41298080e+02 2.99863678e+02
    2.17335251e+02 3.02638489e+02 1.93533279e+02 3.05347870e+02
    1.70092743e+02 3.07849243e+02 3.60072083e+02 2.61481537e+02
    3.35576202e+02 2.64398468e+02 3.11210693e+02 2.67350525e+02
    2.86724762e+02 2.70148651e+02 2.62587433e+02 2.72895782e+02
    2.38514191e+02 2.75670685e+02 2.14496185e+02 2.78604889e+02
    1.90735367e+02 2.81229919e+02 1.67396408e+02 2.83910858e+02
    3.57253479e+02 2.37207916e+02 3.32693604e+02 2.40161423e+02
    3.08348602e+02 2.43112427e+02 2.83988495e+02 2.45927551e+02
    2.59817596e+02 2.48678909e+02 2.35710297e+02 2.51580444e+02
    2.11827362e+02 2.54482620e+02 1.88104950e+02 2.57264801e+02
    1.64639984e+02 2.59959900e+02 3.54436005e+02 2.12877945e+02
    3.29840576e+02 2.15691666e+02 3.05454651e+02 2.18768112e+02
    2.81200684e+02 2.21550018e+02 2.57027802e+02 2.24518784e+02
    2.32961899e+02 2.27432358e+02 2.09101990e+02 2.30464691e+02
    1.85518448e+02 2.33220337e+02 1.62159332e+02 2.36139908e+02
    3.51509033e+02 1.88487976e+02 3.27079742e+02 1.91489746e+02
    3.02644318e+02 1.94477905e+02 2.78419067e+02 1.97462082e+02
    2.54278534e+02 2.00328629e+02 2.30407181e+02 2.03383469e+02
    2.06474579e+02 2.06365311e+02 1.82917084e+02 2.09332870e+02
    1.59545471e+02 2.12309433e+02 3.48670502e+02 1.64246185e+02
    3.24242096e+02 1.67255051e+02 2.99732483e+02 1.70358994e+02
    2.75556061e+02 1.73206055e+02 2.51510529e+02 1.76327957e+02
    2.27489761e+02 1.79390884e+02 2.03813446e+02 1.82431427e+02
    1.80207596e+02 1.85463028e+02 1.57088272e+02 1.88538940e+02
    3.63423218e+02 2.81609894e+02 3.39235229e+02 2.84535522e+02
    3.14915924e+02 2.87396515e+02 2.90653839e+02 2.90313599e+02
    2.66661682e+02 2.93036530e+02 2.42736465e+02 2.95884491e+02
    2.18985962e+02 2.98506897e+02 1.95416397e+02 3.01182556e+02
    1.71994843e+02 3.03728302e+02 3.60519135e+02 2.57636993e+02
    3.36286560e+02 2.60465881e+02 3.11987549e+02 2.63412109e+02
    2.87810638e+02 2.66176514e+02 2.63829559e+02 2.69030426e+02
    2.40003265e+02 2.71718292e+02 2.16270050e+02 2.74653412e+02
    1.92627182e+02 2.77338074e+02 1.69432297e+02 2.80079773e+02
    3.57722839e+02 2.33588379e+02 3.33437653e+02 2.36530533e+02
    3.09245972e+02 2.39375687e+02 2.85143097e+02 2.42302567e+02
    2.61214844e+02 2.44918945e+02 2.37354340e+02 2.47921951e+02
    2.13519653e+02 2.50718353e+02 1.90082108e+02 2.53583054e+02
    1.66825790e+02 2.56372284e+02 3.55004974e+02 2.09504776e+02
    3.30583466e+02 2.12443970e+02 3.06460846e+02 2.15395309e+02
    2.82384094e+02 2.18253677e+02 2.58514618e+02 2.21210464e+02
    2.34568054e+02 2.23973999e+02 2.10915543e+02 2.26991196e+02
    1.87473099e+02 2.29749725e+02 1.64290970e+02 2.32745956e+02
    3.52051239e+02 1.85450989e+02 3.27785889e+02 1.88427109e+02
    3.03552734e+02 1.91398849e+02 2.79527405e+02 1.94402100e+02
    2.55679794e+02 1.97323105e+02 2.31914078e+02 2.00345673e+02
    2.08254303e+02 2.03248672e+02 1.84874557e+02 2.06265411e+02
    1.61749924e+02 2.09201859e+02 3.49260468e+02 1.61473663e+02
    3.24962769e+02 1.64403305e+02 3.00693909e+02 1.67544388e+02
    2.76762451e+02 1.70437500e+02 2.52862259e+02 1.73412262e+02
    2.29145203e+02 1.76487305e+02 2.05669128e+02 1.79521317e+02
    1.82345703e+02 1.82585098e+02 1.59400681e+02 1.85706406e+02
    3.63832153e+02 2.79262787e+02 3.39668365e+02 2.82126465e+02
    3.15517822e+02 2.84836395e+02 2.91357666e+02 2.87702606e+02
    2.67448029e+02 2.90497406e+02 2.43546982e+02 2.93289368e+02
    2.19812439e+02 2.95824127e+02 1.96355438e+02 2.98600220e+02
    1.73076416e+02 3.01159424e+02 3.61170898e+02 2.55218018e+02
    3.36798096e+02 2.57997711e+02 3.12688873e+02 2.60865234e+02
    2.88586395e+02 2.63628479e+02 2.64671539e+02 2.66539612e+02
    2.40802444e+02 2.69242889e+02 2.17193039e+02 2.72075623e+02
    1.93676620e+02 2.74731720e+02 1.70508270e+02 2.77506348e+02
    3.58339844e+02 2.31225677e+02 3.34117981e+02 2.34065826e+02
    3.09912323e+02 2.36810745e+02 2.85889038e+02 2.39713516e+02
    2.62066711e+02 2.42532761e+02 2.38321930e+02 2.45416992e+02
    2.14597290e+02 2.48215851e+02 1.91218903e+02 2.51142578e+02
    1.67902222e+02 2.53727692e+02 3.55489624e+02 2.07125565e+02
    3.31257965e+02 2.09928680e+02 3.07205780e+02 2.12894547e+02
    2.83129089e+02 2.15646271e+02 2.59334808e+02 2.18674179e+02
    2.35574142e+02 2.21538742e+02 2.11875824e+02 2.24436050e+02
    1.88553955e+02 2.27326996e+02 1.65516891e+02 2.30316223e+02
    3.52632935e+02 1.83040955e+02 3.28456757e+02 1.85988205e+02
    3.04323822e+02 1.88809494e+02 2.80411499e+02 1.91864075e+02
    2.56580353e+02 1.94785934e+02 2.32867188e+02 1.97827805e+02
    2.09311707e+02 2.00656723e+02 1.86098999e+02 2.03687256e+02
    1.63034317e+02 2.06679733e+02 3.49838287e+02 1.59004059e+02
    3.25662476e+02 1.61983612e+02 3.01549927e+02 1.65061768e+02
    2.77607819e+02 1.67943848e+02 2.53898132e+02 1.71090485e+02
    2.30226227e+02 1.74030426e+02 2.06827393e+02 1.76981781e+02
    1.83430008e+02 1.80071548e+02 1.60628937e+02 1.83227921e+02
    3.64932831e+02 2.80472015e+02 3.40773987e+02 2.83375153e+02
    3.16684692e+02 2.86125061e+02 2.92612671e+02 2.88940094e+02
    2.68782623e+02 2.91586395e+02 2.45080734e+02 2.94391541e+02
    2.21406784e+02 2.96916443e+02 1.97980728e+02 2.99609283e+02
    1.74820724e+02 3.02240326e+02 3.62273071e+02 2.56500610e+02
    3.38113251e+02 2.59420807e+02 3.13981415e+02 2.62240631e+02
    2.89937378e+02 2.64913116e+02 2.66194244e+02 2.67726562e+02
    2.42407730e+02 2.70497467e+02 2.18728195e+02 2.73253296e+02
    1.95407410e+02 2.75778595e+02 1.72292389e+02 2.78617096e+02
    3.59453156e+02 2.32562317e+02 3.35308594e+02 2.35469620e+02
    3.11245392e+02 2.38279800e+02 2.87313202e+02 2.41078262e+02
    2.63459564e+02 2.43802536e+02 2.39666016e+02 2.46674286e+02
    2.16170166e+02 2.49469620e+02 1.92818039e+02 2.52276031e+02
    1.69628113e+02 2.54936249e+02 3.56593506e+02 2.08594543e+02
    3.32435211e+02 2.11456757e+02 3.08418549e+02 2.14417496e+02
    2.84478516e+02 2.17186798e+02 2.60749603e+02 2.20026535e+02
    2.37019684e+02 2.22828445e+02 2.13499069e+02 2.25736862e+02
    1.90282928e+02 2.28571854e+02 1.67201355e+02 2.31486313e+02
    3.53764038e+02 1.84561081e+02 3.29696564e+02 1.87524841e+02
    3.05642670e+02 1.90469910e+02 2.81755829e+02 1.93397324e+02
    2.58083649e+02 1.96246399e+02 2.34481400e+02 1.99260834e+02
    2.10863800e+02 2.02059814e+02 1.87653381e+02 2.05059326e+02
    1.64566910e+02 2.07831009e+02 3.51114258e+02 1.60568695e+02
    3.26928680e+02 1.63519531e+02 3.02907104e+02 1.66573639e+02
    2.79044403e+02 1.69474487e+02 2.55315933e+02 1.72499680e+02
    2.31652679e+02 1.75499390e+02 2.08327896e+02 1.78578766e+02
    1.85058990e+02 1.81505035e+02 1.62353928e+02 1.84565170e+02
    3.64899933e+02 2.83593536e+02 3.40728210e+02 2.86320648e+02
    3.16593079e+02 2.88821991e+02 2.92478516e+02 2.91494843e+02
    2.68562683e+02 2.93962341e+02 2.44710205e+02 2.96536774e+02
    2.21138611e+02 2.98997192e+02 1.97595398e+02 3.01484222e+02
    1.74444504e+02 3.03776855e+02 3.62416229e+02 2.59542847e+02
    3.38285126e+02 2.62261230e+02 3.14120270e+02 2.64789337e+02
    2.89973907e+02 2.67418823e+02 2.66113342e+02 2.70076630e+02
    2.42370758e+02 2.72560913e+02 2.18683151e+02 2.75238831e+02
    1.95266281e+02 2.77631714e+02 1.72077988e+02 2.80168396e+02
    3.59736420e+02 2.35546875e+02 3.35597809e+02 2.38325089e+02
    3.11533264e+02 2.40912415e+02 2.87490326e+02 2.43560379e+02
    2.63663788e+02 2.46162079e+02 2.39765366e+02 2.48743408e+02
    2.16275803e+02 2.51406158e+02 1.92802795e+02 2.54042923e+02
    1.69702805e+02 2.56469055e+02 3.57279785e+02 2.11570969e+02
    3.32935272e+02 2.14246948e+02 3.08868500e+02 2.16909042e+02
    2.84893066e+02 2.19526367e+02 2.61251801e+02 2.22339905e+02
    2.37411652e+02 2.24862503e+02 2.13837952e+02 2.27640167e+02
    1.90551331e+02 2.30345001e+02 1.67476517e+02 2.33010513e+02
    3.54599518e+02 1.87463913e+02 3.30436737e+02 1.90307892e+02
    3.06417480e+02 1.92931442e+02 2.82424622e+02 1.95722687e+02
    2.58710449e+02 1.98441940e+02 2.35048843e+02 2.01244278e+02
    2.11482468e+02 2.03902786e+02 1.88277695e+02 2.06733200e+02
    1.65225754e+02 2.09498947e+02 3.51975403e+02 1.63548141e+02
    3.27866119e+02 1.66394684e+02 3.03752869e+02 1.69197540e+02
    2.79881195e+02 1.71765533e+02 2.56165741e+02 1.74705856e+02
    2.32466171e+02 1.77495316e+02 2.09169403e+02 1.80355942e+02
    1.85818436e+02 1.83295258e+02 1.63171219e+02 1.86131332e+02
    3.65864746e+02 2.85784332e+02 3.41507050e+02 2.88323334e+02
    3.17084198e+02 2.90765045e+02 2.92685516e+02 2.93266571e+02
    2.68562561e+02 2.95593414e+02 2.44575165e+02 2.98125671e+02
    2.20750626e+02 3.00339233e+02 1.97050339e+02 3.02700287e+02
    1.73639664e+02 3.04920593e+02 3.63411987e+02 2.61569366e+02
    3.38976746e+02 2.64091064e+02 3.14629303e+02 2.66609406e+02
    2.90355072e+02 2.68919373e+02 2.66262604e+02 2.71497925e+02
    2.42340622e+02 2.73811279e+02 2.18453583e+02 2.76319916e+02
    1.94764374e+02 2.78627808e+02 1.71465897e+02 2.81004761e+02
    3.60874969e+02 2.37344391e+02 3.36442871e+02 2.39836426e+02
    3.12175507e+02 2.42428329e+02 2.87950043e+02 2.44894272e+02
    2.63845917e+02 2.47355743e+02 2.39885071e+02 2.49838181e+02
    2.16112762e+02 2.52285812e+02 1.92536987e+02 2.54781555e+02
    1.69225143e+02 2.57123749e+02 3.58495300e+02 2.13060516e+02
    3.33922760e+02 2.15626816e+02 3.09707031e+02 2.18276901e+02
    2.85462860e+02 2.20636642e+02 2.61558929e+02 2.23292953e+02
    2.37594391e+02 2.25723999e+02 2.13765259e+02 2.28372574e+02
    1.90365662e+02 2.30845322e+02 1.67057205e+02 2.33454636e+02
    3.55801300e+02 1.88668091e+02 3.31505951e+02 1.91424622e+02
    3.07260712e+02 1.94086349e+02 2.83079163e+02 1.96589813e+02
    2.59077942e+02 1.99257889e+02 2.35309784e+02 2.01873581e+02
    2.11560287e+02 2.04415359e+02 1.88080704e+02 2.07105743e+02
    1.64849243e+02 2.09700470e+02 3.53308777e+02 1.64614105e+02
    3.29018341e+02 1.67290192e+02 3.04721832e+02 1.70024475e+02
    2.80560669e+02 1.72546783e+02 2.56659790e+02 1.75339417e+02
    2.32811096e+02 1.77943069e+02 2.09324753e+02 1.80607574e+02
    1.85810181e+02 1.83422333e+02 1.62920975e+02 1.86175369e+02
    3.70270874e+02 2.86198181e+02 3.45811920e+02 2.88153625e+02
    3.21443024e+02 2.90194946e+02 2.97074219e+02 2.92117157e+02
    2.72975586e+02 2.93922363e+02 2.48836395e+02 2.95829895e+02
    2.25016312e+02 2.97631805e+02 2.01378220e+02 2.99518036e+02
    1.77883606e+02 3.01313293e+02 3.68192047e+02 2.61911530e+02
    3.43833435e+02 2.63867920e+02 3.19486816e+02 2.65906647e+02
    2.95248779e+02 2.67733276e+02 2.71185883e+02 2.69770142e+02
    2.47170563e+02 2.71646759e+02 2.23304901e+02 2.73677673e+02
    1.99560394e+02 2.75559601e+02 1.76207382e+02 2.77489075e+02
    3.66218781e+02 2.37715118e+02 3.41866486e+02 2.39807175e+02
    3.17545319e+02 2.41771210e+02 2.93420502e+02 2.43760574e+02
    2.69394562e+02 2.45697998e+02 2.45453690e+02 2.47765442e+02
    2.21515289e+02 2.49671936e+02 1.97930801e+02 2.51690170e+02
    1.74648315e+02 2.53597900e+02 3.64240112e+02 2.13610367e+02
    3.39818817e+02 2.15620026e+02 3.15550446e+02 2.17734863e+02
    2.91473602e+02 2.19664078e+02 2.67541534e+02 2.21750809e+02
    2.43616852e+02 2.23728027e+02 2.19778900e+02 2.25919083e+02
    1.96279633e+02 2.27780014e+02 1.73079834e+02 2.29936386e+02
    3.62212708e+02 1.89462875e+02 3.37854797e+02 1.91577591e+02
    3.13613220e+02 1.93686630e+02 2.89582947e+02 1.95802780e+02
    2.65661407e+02 1.97819458e+02 2.41816925e+02 2.00020782e+02
    2.18074356e+02 2.02194626e+02 1.94692291e+02 2.04312210e+02
    1.71514160e+02 2.06419449e+02 3.60188812e+02 1.65480560e+02
    3.35922638e+02 1.67597870e+02 3.11691040e+02 1.69795944e+02
    2.87714264e+02 1.71820465e+02 2.63746826e+02 1.74081116e+02
    2.39935516e+02 1.76257721e+02 2.16427353e+02 1.78511612e+02
    1.92975510e+02 1.80682312e+02 1.70062149e+02 1.83015228e+02
    3.74763824e+02 2.84366486e+02 3.50444061e+02 2.86148651e+02
    3.26100250e+02 2.87712280e+02 3.01670959e+02 2.89569855e+02
    2.77631012e+02 2.91260468e+02 2.53524292e+02 2.92848267e+02
    2.29655090e+02 2.94541504e+02 2.05946594e+02 2.96194824e+02
    1.82433090e+02 2.97706055e+02 3.73021515e+02 2.60113586e+02
    3.48660400e+02 2.61869568e+02 3.24330170e+02 2.63574066e+02
    3.00086639e+02 2.65352905e+02 2.76122803e+02 2.67075531e+02
    2.52036331e+02 2.68657074e+02 2.28148407e+02 2.70499084e+02
    2.04451523e+02 2.72038757e+02 1.81016693e+02 2.73824890e+02
    3.71343445e+02 2.35905640e+02 3.47021484e+02 2.37752625e+02
    3.22698944e+02 2.39505997e+02 2.98565735e+02 2.41284760e+02
    2.74561157e+02 2.42997620e+02 2.50589020e+02 2.44760239e+02
    2.26751740e+02 2.46551437e+02 2.03174850e+02 2.48280334e+02
    1.79672195e+02 2.50060608e+02 3.69578552e+02 2.11838333e+02
    3.45275665e+02 2.13658371e+02 3.20941986e+02 2.15523788e+02
    2.96875366e+02 2.17265625e+02 2.72970123e+02 2.19116150e+02
    2.49116440e+02 2.20780945e+02 2.25339188e+02 2.22749771e+02
    2.01749466e+02 2.24485870e+02 1.78456985e+02 2.26398438e+02
    3.67784943e+02 1.87763580e+02 3.43512329e+02 1.89636795e+02
    3.19367340e+02 1.91540909e+02 2.95340240e+02 1.93397003e+02
    2.71456024e+02 1.95271866e+02 2.47575775e+02 1.97124695e+02
    2.23855087e+02 1.98929825e+02 2.00430176e+02 2.00884003e+02
    1.77145737e+02 2.02784256e+02 3.66148407e+02 1.63843872e+02
    3.41788757e+02 1.65670166e+02 3.17668365e+02 1.67704941e+02
    2.93696686e+02 1.69546051e+02 2.69816864e+02 1.71521652e+02
    2.46056900e+02 1.73370987e+02 2.22572067e+02 1.75293259e+02
    1.98959167e+02 1.77338623e+02 1.75906235e+02 1.79350006e+02
    3.75875275e+02 2.80510040e+02 3.51506531e+02 2.82304260e+02
    3.27192871e+02 2.83920380e+02 3.02780762e+02 2.85626221e+02
    2.78680145e+02 2.87269287e+02 2.54573090e+02 2.88951538e+02
    2.30634399e+02 2.90581055e+02 2.06871094e+02 2.92216309e+02
    1.83345352e+02 2.93715363e+02 3.74254303e+02 2.56344025e+02
    3.49768280e+02 2.58112762e+02 3.25493774e+02 2.59802338e+02
    3.01221161e+02 2.61449921e+02 2.77213226e+02 2.63202209e+02
    2.53194183e+02 2.64775482e+02 2.29279526e+02 2.66633148e+02
    2.05468002e+02 2.68174011e+02 1.82077621e+02 2.69831848e+02
    3.72458954e+02 2.32324463e+02 3.48161560e+02 2.34048508e+02
    3.23859039e+02 2.35730316e+02 2.99656860e+02 2.37506409e+02
    2.75679077e+02 2.39226944e+02 2.51735474e+02 2.40887756e+02
    2.27829819e+02 2.42669983e+02 2.04208649e+02 2.44482193e+02
    1.80782593e+02 2.46135727e+02 3.70852631e+02 2.08186584e+02
    3.46499664e+02 2.09993820e+02 3.22277161e+02 2.11781204e+02
    2.98172272e+02 2.13454300e+02 2.74256256e+02 2.15361252e+02
    2.50326233e+02 2.17042648e+02 2.26505585e+02 2.18869308e+02
    2.02977478e+02 2.20589813e+02 1.79567657e+02 2.22546875e+02
    3.69044281e+02 1.84259491e+02 3.44781342e+02 1.86051788e+02
    3.20616913e+02 1.87817993e+02 2.96552979e+02 1.89711945e+02
    2.72634003e+02 1.91490570e+02 2.48837967e+02 1.93406677e+02
    2.25160645e+02 1.95201523e+02 2.01603714e+02 1.97195511e+02
    1.78479675e+02 1.98975037e+02 3.67407928e+02 1.60375610e+02
    3.43237457e+02 1.62254135e+02 3.19119568e+02 1.64131714e+02
    2.94988464e+02 1.65857422e+02 2.71252380e+02 1.67801239e+02
    2.47392471e+02 1.69625504e+02 2.23734253e+02 1.71626389e+02
    2.00333755e+02 1.73550003e+02 1.77380310e+02 1.75597382e+02
    3.76583160e+02 2.75988403e+02 3.52308228e+02 2.77690277e+02
    3.28029633e+02 2.79481750e+02 3.03658295e+02 2.81226410e+02
    2.79582092e+02 2.82840485e+02 2.55512131e+02 2.84606781e+02
    2.31613434e+02 2.86336914e+02 2.07802826e+02 2.87942078e+02
    1.84335739e+02 2.89553650e+02 3.74871613e+02 2.51802948e+02
    3.50573242e+02 2.53583603e+02 3.26399963e+02 2.55371735e+02
    3.02178833e+02 2.56979767e+02 2.78120911e+02 2.58770874e+02
    2.54109085e+02 2.60500946e+02 2.30271179e+02 2.62342438e+02
    2.06516281e+02 2.63933746e+02 1.83156631e+02 2.65703522e+02
    3.73199066e+02 2.27731430e+02 3.48825165e+02 2.29570282e+02
    3.24683929e+02 2.31350464e+02 3.00570404e+02 2.33150558e+02
    2.76595062e+02 2.34841782e+02 2.52618317e+02 2.36615692e+02
    2.28789810e+02 2.38440689e+02 2.05235626e+02 2.40258270e+02
    1.81755219e+02 2.41918243e+02 3.71512604e+02 2.03757339e+02
    3.47267914e+02 2.05501068e+02 3.23148651e+02 2.07409409e+02
    2.99004669e+02 2.09178741e+02 2.75189117e+02 2.10994675e+02
    2.51257355e+02 2.12734283e+02 2.27473343e+02 2.14675476e+02
    2.03881027e+02 2.16506912e+02 1.80566299e+02 2.18408310e+02
    3.69694214e+02 1.79768188e+02 3.45522858e+02 1.81635300e+02
    3.21441315e+02 1.83545929e+02 2.97469238e+02 1.85421921e+02
    2.73528625e+02 1.87178558e+02 2.49751770e+02 1.89110504e+02
    2.26170822e+02 1.91034668e+02 2.02657562e+02 1.92935455e+02
    1.79430527e+02 1.94933701e+02 3.68007751e+02 1.56030411e+02
    3.43839508e+02 1.57840073e+02 3.19719147e+02 1.59827667e+02
    2.95798553e+02 1.61635162e+02 2.72008453e+02 1.63612762e+02
    2.48268616e+02 1.65499542e+02 2.24705414e+02 1.67532211e+02
    2.01316055e+02 1.69457428e+02 1.78394302e+02 1.71524887e+02
    3.75704773e+02 2.73795929e+02 3.51452118e+02 2.75597076e+02
    3.27140778e+02 2.77315277e+02 3.02760437e+02 2.79125244e+02
    2.78676208e+02 2.80714600e+02 2.54565948e+02 2.82544983e+02
    2.30697830e+02 2.84141235e+02 2.06873611e+02 2.85864716e+02
    1.83343842e+02 2.87483002e+02 3.74099121e+02 2.49649719e+02
    3.49716125e+02 2.51434769e+02 3.25441162e+02 2.53196030e+02
    3.01191681e+02 2.54938339e+02 2.77166168e+02 2.56640625e+02
    2.53221497e+02 2.58424622e+02 2.29252563e+02 2.60180298e+02
    2.05533569e+02 2.61831696e+02 1.82099915e+02 2.63587036e+02
    3.72302917e+02 2.25574890e+02 3.48063141e+02 2.27337326e+02
    3.23758728e+02 2.29181335e+02 2.99622742e+02 2.30936279e+02
    2.75624573e+02 2.32593109e+02 2.51697723e+02 2.34552719e+02
    2.27810257e+02 2.36301529e+02 2.04195480e+02 2.38193863e+02
    1.80725983e+02 2.39803391e+02 3.70597137e+02 2.01599808e+02
    3.46356628e+02 2.03415573e+02 3.22210114e+02 2.05249725e+02
    2.98105194e+02 2.06949432e+02 2.74236755e+02 2.08789322e+02
    2.50307907e+02 2.10717072e+02 2.26512787e+02 2.12528107e+02
    2.02896896e+02 2.14361511e+02 1.79566711e+02 2.16325989e+02
    3.68800446e+02 1.77614044e+02 3.44605774e+02 1.79497437e+02
    3.20474579e+02 1.81328293e+02 2.96472534e+02 1.83284576e+02
    2.72558563e+02 1.85111633e+02 2.48816513e+02 1.87059464e+02
    2.25090927e+02 1.88820831e+02 2.01693771e+02 1.90832703e+02
    1.78472336e+02 1.92732025e+02 3.67178986e+02 1.53828461e+02
    3.43005707e+02 1.55704727e+02 3.18849609e+02 1.57614960e+02
    2.94860474e+02 1.59507446e+02 2.71227112e+02 1.61526001e+02
    2.47347549e+02 1.63425232e+02 2.23779770e+02 1.65417282e+02
    2.00399170e+02 1.67448730e+02 1.77398270e+02 1.69465210e+02
    3.76226532e+02 2.70338226e+02 3.51757965e+02 2.72050751e+02
    3.27469330e+02 2.73709290e+02 3.03237549e+02 2.75571625e+02
    2.79067902e+02 2.77305542e+02 2.55070480e+02 2.79162506e+02
    2.31165924e+02 2.80782166e+02 2.07350372e+02 2.82556213e+02
    1.83779800e+02 2.84233856e+02 3.74402039e+02 2.46159531e+02
    3.50138367e+02 2.47789841e+02 3.25684509e+02 2.49702591e+02
    3.01562592e+02 2.51434967e+02 2.77593750e+02 2.53245163e+02
    2.53541931e+02 2.55061981e+02 2.29603912e+02 2.56800598e+02
    2.05914642e+02 2.58534393e+02 1.82497620e+02 2.60372437e+02
    3.72576874e+02 2.22010635e+02 3.48381042e+02 2.23785980e+02
    3.24118988e+02 2.25664185e+02 2.99971619e+02 2.27506119e+02
    2.75990906e+02 2.29295837e+02 2.52099350e+02 2.31237350e+02
    2.28156494e+02 2.32881897e+02 2.04639450e+02 2.34828995e+02
    1.81303055e+02 2.36564743e+02 3.70942780e+02 1.98053482e+02
    3.46628235e+02 1.99765854e+02 3.22484528e+02 2.01705734e+02
    2.98427673e+02 2.03492081e+02 2.74569489e+02 2.05448013e+02
    2.50666458e+02 2.07306458e+02 2.26783478e+02 2.09269043e+02
    2.03413528e+02 2.11177643e+02 1.80057480e+02 2.13082413e+02
    3.69096466e+02 1.74101700e+02 3.44892853e+02 1.75935181e+02
    3.20736420e+02 1.77797531e+02 2.96728790e+02 1.79771698e+02
    2.72939484e+02 1.81664276e+02 2.49271729e+02 1.83659912e+02
    2.25487289e+02 1.85573532e+02 2.02114563e+02 1.87550339e+02
    1.78928604e+02 1.89563339e+02 3.67364105e+02 1.50347824e+02
    3.43275055e+02 1.52128555e+02 3.19156921e+02 1.54261108e+02
    2.95245483e+02 1.56022202e+02 2.71418274e+02 1.58159286e+02
    2.47630981e+02 1.60104492e+02 2.24256256e+02 1.62137054e+02
    2.00718079e+02 1.64177551e+02 1.77719025e+02 1.66355453e+02
    3.75006134e+02 2.71679077e+02 3.50613281e+02 2.73529907e+02
    3.26304535e+02 2.75287964e+02 3.01853546e+02 2.77027710e+02
    2.77678986e+02 2.78696625e+02 2.53663666e+02 2.80477814e+02
    2.29686447e+02 2.82236481e+02 2.05896423e+02 2.83908478e+02
    1.82376434e+02 2.85534729e+02 3.73296143e+02 2.47476898e+02
    3.48868561e+02 2.49288666e+02 3.24550781e+02 2.51106049e+02
    3.00323029e+02 2.52718109e+02 2.76230896e+02 2.54608780e+02
    2.52190231e+02 2.56396393e+02 2.28244247e+02 2.58265839e+02
    2.04564224e+02 2.59816833e+02 1.81059875e+02 2.61691803e+02
    3.71518585e+02 2.23371780e+02 3.47220856e+02 2.25163940e+02
    3.22916901e+02 2.26989670e+02 2.98732361e+02 2.28784485e+02
    2.74812378e+02 2.30571991e+02 2.50718582e+02 2.32414276e+02
    2.26836960e+02 2.34218201e+02 2.03330414e+02 2.36077957e+02
    1.79754776e+02 2.37874481e+02 3.69772766e+02 1.99333252e+02
    3.45450806e+02 2.01038635e+02 3.21268097e+02 2.02941879e+02
    2.97118073e+02 2.04709763e+02 2.73281830e+02 2.06650040e+02
    2.49283936e+02 2.08517609e+02 2.25526093e+02 2.10431793e+02
    2.01934174e+02 2.12360657e+02 1.78649521e+02 2.14321167e+02
    3.67939697e+02 1.75246796e+02 3.43676086e+02 1.77178635e+02
    3.19573822e+02 1.79114212e+02 2.95550018e+02 1.80944153e+02
    2.71612671e+02 1.82848785e+02 2.47783707e+02 1.84775452e+02
    2.24143829e+02 1.86725616e+02 2.00667816e+02 1.88727295e+02
    1.77473129e+02 1.90684158e+02 3.66344116e+02 1.51403122e+02
    3.42105988e+02 1.53383255e+02 3.17951721e+02 1.55362701e+02
    2.93951202e+02 1.57252823e+02 2.70194916e+02 1.59237503e+02
    2.46352325e+02 1.61190170e+02 2.22863235e+02 1.63279617e+02
    1.99439423e+02 1.65324310e+02 1.76337891e+02 1.67438812e+02
    3.74020599e+02 2.71479309e+02 3.49556793e+02 2.73293640e+02
    3.25229492e+02 2.75088684e+02 3.00744293e+02 2.76822357e+02
    2.76592285e+02 2.78525299e+02 2.52484024e+02 2.80338531e+02
    2.28573914e+02 2.82125916e+02 2.04808456e+02 2.83848877e+02
    1.81380554e+02 2.85522827e+02 3.72269257e+02 2.47216797e+02
    3.47802643e+02 2.49087570e+02 3.23476135e+02 2.50841476e+02
    2.99250031e+02 2.52526413e+02 2.75157410e+02 2.54430161e+02
    2.51040497e+02 2.56189880e+02 2.27170822e+02 2.58086884e+02
    2.03439087e+02 2.59716156e+02 1.79933594e+02 2.61585480e+02
    3.70489716e+02 2.23111664e+02 3.46132050e+02 2.24837448e+02
    3.21755005e+02 2.26713181e+02 2.97587280e+02 2.28572479e+02
    2.73554230e+02 2.30426834e+02 2.49547745e+02 2.32278473e+02
    2.25685135e+02 2.33981995e+02 2.02160904e+02 2.35970093e+02
    1.78717850e+02 2.37771011e+02 3.68658875e+02 1.98898575e+02
    3.44281952e+02 2.00692734e+02 3.20070496e+02 2.02676208e+02
    2.95917694e+02 2.04449326e+02 2.71934631e+02 2.06472443e+02
    2.48061264e+02 2.08317215e+02 2.24380707e+02 2.10351837e+02
    2.00750900e+02 2.12251495e+02 1.77491013e+02 2.14234619e+02
    3.66861664e+02 1.74745026e+02 3.42555634e+02 1.76733139e+02
    3.18419067e+02 1.78760956e+02 2.94418457e+02 1.80668640e+02
    2.70463989e+02 1.82583725e+02 2.46624512e+02 1.84632446e+02
    2.22985535e+02 1.86614563e+02 1.99560471e+02 1.88615753e+02
    1.76279694e+02 1.90643051e+02 3.65097076e+02 1.50997955e+02
    3.40799438e+02 1.52902054e+02 3.16681366e+02 1.55006775e+02
    2.92692841e+02 1.56868637e+02 2.68822632e+02 1.58986481e+02
    2.45126251e+02 1.60896774e+02 2.21632141e+02 1.63106964e+02
    1.98252640e+02 1.65189056e+02 1.75287201e+02 1.67359207e+02
    3.73606873e+02 2.70086670e+02 3.49212646e+02 2.71722046e+02
    3.24740967e+02 2.73559692e+02 3.00379944e+02 2.75383392e+02
    2.76286621e+02 2.76924866e+02 2.52148499e+02 2.78786591e+02
    2.28250870e+02 2.80484741e+02 2.04490723e+02 2.82246155e+02
    1.80944778e+02 2.83786621e+02 3.71745758e+02 2.45819763e+02
    3.47435760e+02 2.47584991e+02 3.23175629e+02 2.49387436e+02
    2.98860870e+02 2.51114914e+02 2.74808258e+02 2.52846390e+02
    2.50752930e+02 2.54622269e+02 2.26794205e+02 2.56444885e+02
    2.03257919e+02 2.58227600e+02 1.79688385e+02 2.59981903e+02
    3.70103027e+02 2.21655273e+02 3.45697723e+02 2.23533508e+02
    3.21447876e+02 2.25337875e+02 2.97321899e+02 2.27159653e+02
    2.73304596e+02 2.28842514e+02 2.49391830e+02 2.30716751e+02
    2.25491119e+02 2.32508209e+02 2.01891312e+02 2.34456650e+02
    1.78577148e+02 2.36179276e+02 3.68318939e+02 1.97609695e+02
    3.43878540e+02 1.99425720e+02 3.19680725e+02 2.01351318e+02
    2.95673035e+02 2.03221588e+02 2.71691925e+02 2.05054230e+02
    2.47819443e+02 2.06896591e+02 2.24147842e+02 2.08792282e+02
    2.00611282e+02 2.10687592e+02 1.77406708e+02 2.12624451e+02
    3.66568054e+02 1.73539230e+02 3.42329865e+02 1.75454956e+02
    3.18142059e+02 1.77407547e+02 2.94204071e+02 1.79408554e+02
    2.70255127e+02 1.81261292e+02 2.46511505e+02 1.83223251e+02
    2.22808182e+02 1.85234848e+02 1.99438339e+02 1.87290970e+02
    1.76198212e+02 1.89242538e+02 3.64762848e+02 1.49719147e+02
    3.40554718e+02 1.51674622e+02 3.16429474e+02 1.53743057e+02
    2.92477631e+02 1.55632034e+02 2.68690125e+02 1.57675018e+02
    2.44966797e+02 1.59595200e+02 2.21562775e+02 1.61665878e+02
    1.98161316e+02 1.63733658e+02 1.75271072e+02 1.65953705e+02
    3.74882019e+02 2.66876892e+02 3.50524475e+02 2.68603363e+02
    3.26234222e+02 2.70393341e+02 3.01963898e+02 2.72133087e+02
    2.77794952e+02 2.73776794e+02 2.53775192e+02 2.75662537e+02
    2.29895844e+02 2.77415466e+02 2.06254654e+02 2.79186768e+02
    1.82775604e+02 2.80819733e+02 3.73078644e+02 2.42720093e+02
    3.48738434e+02 2.44429733e+02 3.24495636e+02 2.46334229e+02
    3.00311340e+02 2.47898865e+02 2.76313110e+02 2.49811096e+02
    2.52326904e+02 2.51569839e+02 2.28417618e+02 2.53439041e+02
    2.04801849e+02 2.55258530e+02 1.81487839e+02 2.57032501e+02
    3.71349701e+02 2.18594849e+02 3.47103302e+02 2.20418884e+02
    3.22833282e+02 2.22282745e+02 2.98721252e+02 2.24122406e+02
    2.74783478e+02 2.25890121e+02 2.50820206e+02 2.27751785e+02
    2.27151306e+02 2.29589844e+02 2.03582153e+02 2.31502670e+02
    1.80255783e+02 2.33341003e+02 3.69550903e+02 1.94633179e+02
    3.45274170e+02 1.96387970e+02 3.21139709e+02 1.98403000e+02
    2.97095795e+02 2.00148758e+02 2.73353699e+02 2.02067230e+02
    2.49400085e+02 2.03893143e+02 2.25665085e+02 2.05944168e+02
    2.02347794e+02 2.07725586e+02 1.79170380e+02 2.09793060e+02
    3.67689728e+02 1.70689499e+02 3.43541565e+02 1.72548065e+02
    3.19472137e+02 1.74538986e+02 2.95461823e+02 1.76481674e+02
    2.71684479e+02 1.78408096e+02 2.47944046e+02 1.80442612e+02
    2.24324066e+02 1.82411118e+02 2.01165451e+02 1.84373367e+02
    1.77918503e+02 1.86457123e+02 3.66018097e+02 1.46948959e+02
    3.41810852e+02 1.48890442e+02 3.17761932e+02 1.50966400e+02
    2.93868927e+02 1.52795639e+02 2.70244507e+02 1.54869537e+02
    2.46501419e+02 1.56825119e+02 2.23161041e+02 1.58905182e+02
    1.99649689e+02 1.61007782e+02 1.76854477e+02 1.63217239e+02
    3.75468109e+02 2.67754272e+02 3.51199951e+02 2.69559174e+02
    3.26808716e+02 2.71363373e+02 3.02487335e+02 2.73101166e+02
    2.78416656e+02 2.74718567e+02 2.54318558e+02 2.76474243e+02
    2.30430542e+02 2.78155945e+02 2.06686264e+02 2.79812073e+02
    1.83309265e+02 2.81470886e+02 3.73751373e+02 2.43660843e+02
    3.49416534e+02 2.45396423e+02 3.25177551e+02 2.47185547e+02
    3.00858459e+02 2.48856125e+02 2.76831512e+02 2.50679092e+02
    2.52890884e+02 2.52374725e+02 2.29010757e+02 2.54265991e+02
    2.05382782e+02 2.55818298e+02 1.81998596e+02 2.57616882e+02
    3.72014709e+02 2.19512451e+02 3.47691162e+02 2.21382507e+02
    3.23480530e+02 2.23183212e+02 2.99406097e+02 2.24894012e+02
    2.75409973e+02 2.26662582e+02 2.51493179e+02 2.28456650e+02
    2.27649567e+02 2.30351364e+02 2.04133560e+02 2.32152817e+02
    1.80684143e+02 2.33866592e+02 3.70344452e+02 1.95564606e+02
    3.45976135e+02 1.97374573e+02 3.21838226e+02 1.99266647e+02
    2.97770874e+02 2.00886551e+02 2.73880524e+02 2.02835342e+02
    2.50047821e+02 2.04683578e+02 2.26402283e+02 2.06629135e+02
    2.02873032e+02 2.08385513e+02 1.79603851e+02 2.10411163e+02
    3.68510406e+02 1.71579269e+02 3.44352844e+02 1.73422485e+02
    3.20218536e+02 1.75385422e+02 2.96311920e+02 1.77323502e+02
    2.72381226e+02 1.79196823e+02 2.48665909e+02 1.81081619e+02
    2.24986938e+02 1.83015488e+02 2.01640121e+02 1.85001709e+02
    1.78524521e+02 1.87019836e+02 3.66757751e+02 1.47816391e+02
    3.42729126e+02 1.49745377e+02 3.18614380e+02 1.51716354e+02
    2.94734467e+02 1.53591644e+02 2.71003174e+02 1.55608063e+02
    2.47258255e+02 1.57553101e+02 2.23724121e+02 1.59552856e+02
    2.00390915e+02 1.61608871e+02 1.77465988e+02 1.63717697e+02
    3.75664154e+02 2.64658112e+02 3.51408356e+02 2.66534637e+02
    3.27138733e+02 2.68290100e+02 3.02765137e+02 2.70146606e+02
    2.78754150e+02 2.71817841e+02 2.54650742e+02 2.73701904e+02
    2.30812836e+02 2.75476318e+02 2.07203827e+02 2.77267151e+02
    1.83636459e+02 2.79079407e+02 3.73892426e+02 2.40450165e+02
    3.49547485e+02 2.42340622e+02 3.25407837e+02 2.44148056e+02
    3.01163208e+02 2.45853882e+02 2.77191254e+02 2.47729248e+02
    2.53200272e+02 2.49591492e+02 2.29404892e+02 2.51492004e+02
    2.05733231e+02 2.53363846e+02 1.82394669e+02 2.55251831e+02
    3.72050812e+02 2.16358765e+02 3.47797455e+02 2.18326645e+02
    3.23623688e+02 2.20157104e+02 2.99538452e+02 2.22093994e+02
    2.75579132e+02 2.23804413e+02 2.51692551e+02 2.25854736e+02
    2.27890274e+02 2.27640930e+02 2.04425858e+02 2.29612778e+02
    1.81104019e+02 2.31460754e+02 3.70340546e+02 1.92390991e+02
    3.46091858e+02 1.94329468e+02 3.21901672e+02 1.96220749e+02
    2.97901398e+02 1.98026215e+02 2.74061340e+02 2.00043930e+02
    2.50294434e+02 2.01968399e+02 2.26520981e+02 2.03948242e+02
    2.03219391e+02 2.05911682e+02 1.79898087e+02 2.07964569e+02
    3.68396790e+02 1.68394531e+02 3.44289124e+02 1.70410431e+02
    3.20141205e+02 1.72417496e+02 2.96295380e+02 1.74425446e+02
    2.72415863e+02 1.76334320e+02 2.48748764e+02 1.78414658e+02
    2.25151749e+02 1.80411896e+02 2.01810013e+02 1.82536545e+02
    1.78789047e+02 1.84567245e+02 3.66614532e+02 1.44690033e+02
    3.42540863e+02 1.46740799e+02 3.18482819e+02 1.48760300e+02
    2.94665405e+02 1.50734772e+02 2.70876221e+02 1.52809769e+02
    2.47248489e+02 1.54885544e+02 2.23749619e+02 1.56923294e+02
    2.00477188e+02 1.59213394e+02 1.77616089e+02 1.61370483e+02
    3.76153137e+02 2.65220062e+02 3.51712555e+02 2.67054840e+02
    3.27434601e+02 2.68746582e+02 3.03197876e+02 2.70631317e+02
    2.79078613e+02 2.72348999e+02 2.55124207e+02 2.74221527e+02
    2.31181305e+02 2.75885712e+02 2.07437927e+02 2.77684967e+02
    1.83979736e+02 2.79413055e+02 3.74360535e+02 2.40922775e+02
    3.50025635e+02 2.42786621e+02 3.25672882e+02 2.44613678e+02
    3.01490753e+02 2.46452637e+02 2.77527039e+02 2.48292358e+02
    2.53579025e+02 2.50180237e+02 2.29624008e+02 2.51969650e+02
    2.06109741e+02 2.53730179e+02 1.82709518e+02 2.55594482e+02
    3.72503937e+02 2.16903534e+02 3.48273987e+02 2.18762665e+02
    3.23934174e+02 2.20573837e+02 2.99833527e+02 2.22551132e+02
    2.75925537e+02 2.24346558e+02 2.52087250e+02 2.26300797e+02
    2.28294189e+02 2.28032028e+02 2.04725845e+02 2.30123184e+02
    1.81549271e+02 2.31848099e+02 3.70788818e+02 1.92845825e+02
    3.46503967e+02 1.94739822e+02 3.22341064e+02 1.96613678e+02
    2.98308533e+02 1.98549652e+02 2.74475647e+02 2.00486679e+02
    2.50580276e+02 2.02445587e+02 2.26845856e+02 2.04403397e+02
    2.03473557e+02 2.06432632e+02 1.80317795e+02 2.08383896e+02
    3.68906799e+02 1.68841736e+02 3.44666412e+02 1.70871338e+02
    3.20560913e+02 1.72789474e+02 2.96622589e+02 1.74851212e+02
    2.72800995e+02 1.76755249e+02 2.49199646e+02 1.78847748e+02
    2.25449036e+02 1.80756912e+02 2.02219162e+02 1.82956573e+02
    1.79181549e+02 1.84928558e+02 3.67196533e+02 1.45093628e+02
    3.43016937e+02 1.47196274e+02 3.18955475e+02 1.49236481e+02
    2.95096619e+02 1.51209045e+02 2.71325104e+02 1.53340881e+02
    2.47575333e+02 1.55409897e+02 2.24233871e+02 1.57427811e+02
    2.00765457e+02 1.59578125e+02 1.78056076e+02 1.61779922e+02
    3.75971497e+02 2.65186798e+02 3.51540497e+02 2.66907349e+02
    3.27256653e+02 2.68592468e+02 3.02862793e+02 2.70486938e+02
    2.78714600e+02 2.72008606e+02 2.54706879e+02 2.73798981e+02
    2.30824982e+02 2.75544434e+02 2.07194504e+02 2.77286591e+02
    1.83647507e+02 2.78927246e+02 3.74269012e+02 2.40908798e+02
    3.49845856e+02 2.42731552e+02 3.25533051e+02 2.44480103e+02
    3.01344116e+02 2.46294662e+02 2.77398621e+02 2.48006958e+02
    2.53304886e+02 2.49697571e+02 2.29434128e+02 2.51583496e+02
    2.05856720e+02 2.53340302e+02 1.82452042e+02 2.55172714e+02
    3.72448608e+02 2.16803268e+02 3.48200470e+02 2.18649017e+02
    3.23896851e+02 2.20475540e+02 2.99810760e+02 2.22307251e+02
    2.75758759e+02 2.23997360e+02 2.51907608e+02 2.25922409e+02
    2.28099731e+02 2.27688400e+02 2.04587219e+02 2.29571930e+02
    1.81324036e+02 2.31378098e+02 3.70776672e+02 1.92765350e+02
    3.46466827e+02 1.94610062e+02 3.22323120e+02 1.96501389e+02
    2.98271271e+02 1.98353958e+02 2.74406677e+02 2.00267960e+02
    2.50553925e+02 2.02102280e+02 2.26791275e+02 2.04057373e+02
    2.03419907e+02 2.05948456e+02 1.80264450e+02 2.07805115e+02
    3.68990723e+02 1.68757141e+02 3.44770447e+02 1.70667740e+02
    3.20579102e+02 1.72660660e+02 2.96625763e+02 1.74684052e+02
    2.72795166e+02 1.76496490e+02 2.49184601e+02 1.78540710e+02
    2.25464157e+02 1.80442673e+02 2.02314484e+02 1.82518051e+02
    1.79184494e+02 1.84497101e+02 3.67266724e+02 1.44999176e+02
    3.43242401e+02 1.47094238e+02 3.19115387e+02 1.49068802e+02
    2.95143829e+02 1.50955811e+02 2.71429535e+02 1.52983765e+02
    2.47673386e+02 1.55056595e+02 2.24301193e+02 1.57019073e+02
    2.00958496e+02 1.59271149e+02 1.78149002e+02 1.61385040e+02
    3.76111877e+02 2.63406372e+02 3.51689087e+02 2.65195953e+02
    3.27376984e+02 2.67045746e+02 3.03013336e+02 2.68784973e+02
    2.78889282e+02 2.70527008e+02 2.54808228e+02 2.72329742e+02
    2.30892044e+02 2.74083374e+02 2.07242844e+02 2.75796661e+02
    1.83662445e+02 2.77582947e+02 3.74372986e+02 2.39242020e+02
    3.50009674e+02 2.41075775e+02 3.25601074e+02 2.42823868e+02
    3.01415497e+02 2.44546875e+02 2.77416016e+02 2.46488358e+02
    2.53376831e+02 2.48223145e+02 2.29480621e+02 2.50151276e+02
    2.05820190e+02 2.51808823e+02 1.82471985e+02 2.53761536e+02
    3.72540985e+02 2.15091049e+02 3.48275360e+02 2.16858047e+02
    3.23858154e+02 2.18743256e+02 2.99735413e+02 2.20653976e+02
    2.75761780e+02 2.22467133e+02 2.51918869e+02 2.24367722e+02
    2.28041077e+02 2.26280319e+02 2.04554947e+02 2.28128036e+02
    1.81327667e+02 2.30020142e+02 3.70876404e+02 1.91073456e+02
    3.46455231e+02 1.92779587e+02 3.22321899e+02 1.94834534e+02
    2.98243408e+02 1.96625244e+02 2.74326233e+02 1.98593674e+02
    2.50478821e+02 2.00521927e+02 2.26697235e+02 2.02564423e+02
    2.03330490e+02 2.04443649e+02 1.80115875e+02 2.06539459e+02
    3.68974243e+02 1.67032104e+02 3.44673767e+02 1.68976898e+02
    3.20535767e+02 1.71082367e+02 2.96588196e+02 1.72890701e+02
    2.72703064e+02 1.74841354e+02 2.49079895e+02 1.76959976e+02
    2.25448166e+02 1.78984924e+02 2.02092072e+02 1.81074478e+02
    1.79051544e+02 1.83161118e+02 3.67238403e+02 1.43260284e+02
    3.43100281e+02 1.45332581e+02 3.19003754e+02 1.47362213e+02
    2.95014282e+02 1.49313873e+02 2.71327362e+02 1.51365067e+02
    2.47551941e+02 1.53387924e+02 2.24193954e+02 1.55478668e+02
    2.00774826e+02 1.57641556e+02 1.77913773e+02 1.59823746e+02
    3.76327576e+02 2.62476990e+02 3.51947357e+02 2.64208893e+02
    3.27593048e+02 2.65980988e+02 3.03332001e+02 2.67796844e+02
    2.79217133e+02 2.69576172e+02 2.55253754e+02 2.71418945e+02
    2.31308624e+02 2.73241302e+02 2.07489059e+02 2.75108551e+02
    1.84071075e+02 2.76662537e+02 3.74541870e+02 2.38313889e+02
    3.50183044e+02 2.39998764e+02 3.25829803e+02 2.41882919e+02
    3.01641968e+02 2.43651703e+02 2.77590027e+02 2.45567673e+02
    2.53664749e+02 2.47410156e+02 2.29761353e+02 2.49296692e+02
    2.06218262e+02 2.51007050e+02 1.82790131e+02 2.52896255e+02
    3.72691864e+02 2.14170547e+02 3.48435425e+02 2.15930710e+02
    3.24147919e+02 2.17857590e+02 3.00037933e+02 2.19783310e+02
    2.76039703e+02 2.21588165e+02 2.52209274e+02 2.23543945e+02
    2.28426971e+02 2.25442337e+02 2.04820740e+02 2.27388397e+02
    1.81598679e+02 2.29235199e+02 3.71051300e+02 1.90187546e+02
    3.46629486e+02 1.91951004e+02 3.22510345e+02 1.93968781e+02
    2.98432739e+02 1.95731812e+02 2.74639832e+02 1.97754852e+02
    2.50727646e+02 1.99735352e+02 2.27105774e+02 2.01730560e+02
    2.03568344e+02 2.03626907e+02 1.80438843e+02 2.05727158e+02
    3.69116882e+02 1.66193359e+02 3.44884155e+02 1.68125183e+02
    3.20726562e+02 1.70159546e+02 2.96745728e+02 1.72085083e+02
    2.73010101e+02 1.74120697e+02 2.49393692e+02 1.76160568e+02
    2.25697769e+02 1.78196793e+02 2.02416107e+02 1.80275131e+02
    1.79322708e+02 1.82386612e+02 3.67326996e+02 1.42488464e+02
    3.43268280e+02 1.44421967e+02 3.19198547e+02 1.46568832e+02
    2.95262024e+02 1.48459000e+02 2.71471252e+02 1.50583282e+02
    2.47732269e+02 1.52673172e+02 2.24420761e+02 1.54747375e+02
    2.01075989e+02 1.56944794e+02 1.78286621e+02 1.59212051e+02
    3.75557251e+02 2.62085144e+02 3.51241791e+02 2.63834412e+02
    3.26862061e+02 2.65679443e+02 3.02548279e+02 2.67498383e+02
    2.78445160e+02 2.69225281e+02 2.54445358e+02 2.71104309e+02
    2.30516586e+02 2.72827820e+02 2.06839447e+02 2.74702362e+02
    1.83386551e+02 2.76380981e+02 3.73737061e+02 2.37858841e+02
    3.49426727e+02 2.39669662e+02 3.25177368e+02 2.41543427e+02
    3.00926514e+02 2.43312820e+02 2.76855011e+02 2.45213425e+02
    2.52973282e+02 2.47025085e+02 2.29045654e+02 2.48892380e+02
    2.05487747e+02 2.50685867e+02 1.82149719e+02 2.52542526e+02
    3.71950256e+02 2.13785370e+02 3.47643890e+02 2.15607666e+02
    3.23450439e+02 2.17509201e+02 2.99371490e+02 2.19439407e+02
    2.75425171e+02 2.21301071e+02 2.51511932e+02 2.23275375e+02
    2.27649429e+02 2.24995041e+02 2.04255142e+02 2.27098114e+02
    1.80872025e+02 2.28828506e+02 3.70227295e+02 1.89759827e+02
    3.45845062e+02 1.91613846e+02 3.21719269e+02 1.93604752e+02
    2.97702301e+02 1.95537003e+02 2.73799744e+02 1.97500183e+02
    2.49958466e+02 1.99390762e+02 2.26407730e+02 2.01427414e+02
    2.02919540e+02 2.03407181e+02 1.79665268e+02 2.05430832e+02
    3.68294098e+02 1.65864288e+02 3.44155457e+02 1.67776550e+02
    3.19984680e+02 1.69778137e+02 2.96156586e+02 1.71756439e+02
    2.72256409e+02 1.73722641e+02 2.48560867e+02 1.75799210e+02
    2.24965271e+02 1.77829407e+02 2.01676208e+02 1.79943756e+02
    1.78524048e+02 1.82060516e+02 3.66520508e+02 1.42137146e+02
    3.42459076e+02 1.44056976e+02 3.18394836e+02 1.46270401e+02
    2.94498474e+02 1.48182343e+02 2.70701904e+02 1.50317795e+02
    2.47069550e+02 1.52335648e+02 2.23632584e+02 1.54488770e+02
    2.00320694e+02 1.56571396e+02 1.77441574e+02 1.58866562e+02
    3.75702057e+02 2.62519714e+02 3.51467377e+02 2.64371674e+02
    3.27220276e+02 2.66204865e+02 3.02860199e+02 2.67970673e+02
    2.78843048e+02 2.69702026e+02 2.54833664e+02 2.71576538e+02
    2.30996445e+02 2.73363556e+02 2.07396835e+02 2.75259277e+02
    1.83933395e+02 2.76901550e+02 3.73934235e+02 2.38413498e+02
    3.49623383e+02 2.40176483e+02 3.25436676e+02 2.42120499e+02
    3.01254761e+02 2.43831497e+02 2.77289856e+02 2.45709732e+02
    2.53395508e+02 2.47573044e+02 2.29511383e+02 2.49480652e+02
    2.05934769e+02 2.51310822e+02 1.82595825e+02 2.53178131e+02
    3.72043884e+02 2.14394119e+02 3.47856171e+02 2.16220673e+02
    3.23629578e+02 2.18166275e+02 2.99574463e+02 2.19987625e+02
    2.75707214e+02 2.21791504e+02 2.51838364e+02 2.23739426e+02
    2.28086105e+02 2.25643387e+02 2.04624802e+02 2.27579422e+02
    1.81436996e+02 2.29506332e+02 3.70371246e+02 1.90397629e+02
    3.46066559e+02 1.92254349e+02 3.21958099e+02 1.94280899e+02
    2.97953247e+02 1.95977539e+02 2.74181488e+02 1.98052841e+02
    2.50393982e+02 2.00006622e+02 2.26712601e+02 2.02084244e+02
    2.03410065e+02 2.03902008e+02 1.80224365e+02 2.06122116e+02
    3.68464783e+02 1.66472198e+02 3.44341553e+02 1.68404953e+02
    3.20223785e+02 1.70409180e+02 2.96361908e+02 1.72389359e+02
    2.72529724e+02 1.74441315e+02 2.49018326e+02 1.76427948e+02
    2.25325607e+02 1.78519867e+02 2.02087799e+02 1.80504837e+02
    1.79047104e+02 1.82685791e+02 3.66605621e+02 1.42763336e+02
    3.42560608e+02 1.44721695e+02 3.18534027e+02 1.46881485e+02
    2.94741058e+02 1.48775925e+02 2.71062347e+02 1.50934967e+02
    2.47401688e+02 1.52966949e+02 2.23996231e+02 1.55176544e+02
    2.00718765e+02 1.57348343e+02 1.77854813e+02 1.59577377e+02
    3.76261658e+02 2.61408844e+02 3.52018066e+02 2.63316742e+02
    3.27755188e+02 2.65150543e+02 3.03592499e+02 2.66989746e+02
    2.79567993e+02 2.68681244e+02 2.55591156e+02 2.70678467e+02
    2.31724564e+02 2.72428223e+02 2.08206818e+02 2.74351807e+02
    1.84757172e+02 2.75978516e+02 3.74475281e+02 2.37406952e+02
    3.50278931e+02 2.39284729e+02 3.26115051e+02 2.41147217e+02
    3.01968597e+02 2.42981781e+02 2.78097046e+02 2.44707901e+02
    2.54134674e+02 2.46630875e+02 2.30386765e+02 2.48545837e+02
    2.06794876e+02 2.50482941e+02 1.83454605e+02 2.52335266e+02
    3.72618042e+02 2.13451172e+02 3.48424713e+02 2.15289185e+02
    3.24336639e+02 2.17258316e+02 3.00363770e+02 2.19205444e+02
    2.76416138e+02 2.20980545e+02 2.52595428e+02 2.23027603e+02
    2.28897873e+02 2.24824631e+02 2.05460846e+02 2.26831055e+02
    1.82241364e+02 2.28692276e+02 3.70881226e+02 1.89513596e+02
    3.46613037e+02 1.91445877e+02 3.22592285e+02 1.93448547e+02
    2.98668976e+02 1.95346741e+02 2.74880066e+02 1.97288895e+02
    2.51128784e+02 1.99314667e+02 2.27544281e+02 2.01328217e+02
    2.04139603e+02 2.03320938e+02 1.80949097e+02 2.05422989e+02
    3.68900146e+02 1.65662186e+02 3.44852905e+02 1.67651901e+02
    3.20818329e+02 1.69635376e+02 2.97027557e+02 1.71750015e+02
    2.73292267e+02 1.73726105e+02 2.49625626e+02 1.75755234e+02
    2.26176285e+02 1.77804443e+02 2.02870407e+02 1.79927948e+02
    1.79768906e+02 1.82071014e+02 3.67207947e+02 1.42128082e+02
    3.43178314e+02 1.44076645e+02 3.19242615e+02 1.46293472e+02
    2.95376678e+02 1.48227554e+02 2.71662415e+02 1.50358109e+02
    2.48063599e+02 1.52393951e+02 2.24732285e+02 1.54568726e+02
    2.01488022e+02 1.56629745e+02 1.78707916e+02 1.58963608e+02</data></image_points>
</opencv_storage>
