<?xml version="1.0"?>
<opencv_storage>
<calibration_time>"Thu 02 Mar 2017 03:22:16 PM PST"</calibration_time>
<nr_of_frames>25</nr_of_frames>
<image_width>2080</image_width>
<image_height>1552</image_height>
<board_width>9</board_width>
<board_height>6</board_height>
<square_size>9.3900002539157867e-03</square_size>
<fix_aspect_ratio>1.</fix_aspect_ratio>
<!-- flags: +fix_aspectRatio +fix_principal_point +zero_tangent_dist -->
<flags>6158</flags>
<fisheye_model>0</fisheye_model>
<camera_matrix type_id="opencv-matrix">
  <rows>3</rows>
  <cols>3</cols>
  <dt>d</dt>
  <data>
    5.3113301947478431e+03 0. 1.0395000000000000e+03 0.
    5.3113301947478431e+03 7.7550000000000000e+02 0. 0. 1.</data></camera_matrix>
<distortion_coefficients type_id="opencv-matrix">
  <rows>5</rows>
  <cols>1</cols>
  <dt>d</dt>
  <data>
    -1.5354329283341409e-01 8.8391449185375528e+00 0. 0.
    -5.6809828366090876e+01</data></distortion_coefficients>
<avg_reprojection_error>1.7219729399861816e+00</avg_reprojection_error>
<per_view_reprojection_errors type_id="opencv-matrix">
  <rows>25</rows>
  <cols>1</cols>
  <dt>f</dt>
  <data>
    1.54603910e+00 1.55028784e+00 1.55188310e+00 1.55266261e+00
    1.73957038e+00 2.08992100e+00 2.79924560e+00 2.03168511e+00
    2.21303487e+00 1.71315610e+00 1.88788438e+00 1.39421153e+00
    1.46978390e+00 2.11488533e+00 2.27716851e+00 1.59079885e+00
    1.68925893e+00 1.35612702e+00 1.03198600e+00 1.26126778e+00
    1.41652298e+00 1.42002809e+00 1.41678882e+00 1.43087173e+00
    1.42967546e+00</data></per_view_reprojection_errors>
<extrinsic_parameters type_id="opencv-matrix">
  <rows>25</rows>
  <cols>6</cols>
  <dt>d</dt>
  <data>
    -7.5460199649077775e-01 -5.4660393262539228e-02
    2.8877793925877106e-02 -4.1232459159249113e-02
    7.2132373675493459e-03 5.2410646567779962e-01
    -7.5464281893820728e-01 -5.4737058532871752e-02
    2.8888654502416178e-02 -4.1227286001037096e-02
    7.2189816046219820e-03 5.2411685304898181e-01
    -7.5458255336595748e-01 -5.4630229791999635e-02
    2.8887428022667510e-02 -4.1225412598911659e-02
    7.2237309011743316e-03 5.2411444556396214e-01
    -7.5458355154179202e-01 -5.4656155309608032e-02
    2.8885298281587896e-02 -4.1226717802835704e-02
    7.2202868724652331e-03 5.2411632486669191e-01
    -8.3344658514752501e-01 -7.2004895502539301e-02
    1.3006992917489146e-02 -4.0596576472099473e-02
    8.7984768737559317e-03 5.2043149961263602e-01
    -3.5839352897210464e-02 -1.9401427236613469e-01
    3.3106252714248399e-02 -3.4770267470575884e-02
    -3.2264664352902657e-02 5.0032260215585322e-01
    2.6177598954806352e-02 1.4117890289765858e-01
    -5.8702703506513260e-04 -7.1215151103159680e-02
    -4.0768843585385954e-02 5.1272975810488930e-01
    -2.6459616484549020e-01 -1.1236921543473398e-01
    -4.4038493090343633e-02 -7.5808651191834733e-02
    8.7334294409330965e-03 4.9040525114745614e-01 9.5900309438184228e-02
    -1.9922290285995856e-01 -5.6434614456466935e-02
    -3.5680928563630046e-02 -6.1526225074682694e-02
    4.8538805028647747e-01 8.3607791108251700e-02
    -2.3487905190730604e-01 1.9924136253857330e-02
    -2.6053247027948159e-02 -5.9902026447818862e-02
    4.9427121258864143e-01 1.9870897375527014e-01
    -3.3502471578206017e-01 1.0769346971205853e+00
    1.2168476366842323e-02 -6.1986587405908511e-02
    4.3659129614098480e-01 4.1484253118107073e-01
    -4.7398985076245409e-01 1.5943311108290918e+00
    5.1976044446098636e-02 -4.3331772842653916e-02
    4.4480004871533191e-01 2.8345115620823893e-02 1.4141458662607581e-01
    2.8318765234050077e-02 -9.1919093970474847e-02
    -4.0547051687570883e-02 5.0668968515057333e-01
    7.3415339104567517e-02 -2.0924792683105689e-01
    1.1946869082259535e-02 -3.3908148065536173e-02
    -4.9758445271059361e-02 5.0567078713965430e-01
    6.8772660664886798e-02 -2.0738708066395789e-01
    1.6660870188783348e-02 -3.5601911813724227e-02
    -4.9596163398857668e-02 5.0560763830642530e-01
    -1.3863904015611975e-01 -8.9579161648981789e-02
    5.0214118647023180e-02 -3.5296581763816628e-02
    -2.4022790326778985e-02 5.0626662553281510e-01
    -2.1878132899307834e-01 -7.5834546724329252e-02
    4.4056329075408476e-02 -3.9404800726742704e-02
    -1.2409383471022216e-02 4.9544527293974833e-01
    -4.3750419058886786e-01 -4.1586921018336456e-02
    6.7474144878863149e-02 -4.3151244335733668e-02
    5.5674394895909446e-03 4.9754143322719391e-01 2.5506671447777129e-01
    -5.5687621676837280e-02 1.3262068430963569e-02
    -1.7725725731836766e-02 -6.4726075555014501e-02
    5.2627269742364957e-01 5.5598370472736927e-02 1.3030758359231520e-01
    2.9653739724765323e-02 -9.1520496491459657e-02
    -5.7524274566277296e-02 4.8264988620978216e-01
    -6.9146354748633732e-01 -5.3533617571275477e-02
    3.7394851881799106e-02 -4.1808002924349517e-02
    -8.1177141476509781e-03 5.3532760849806538e-01
    -6.9238292541995061e-01 -5.3435262915381053e-02
    3.7545215526348388e-02 -4.1805864783308340e-02
    -8.0879316472968216e-03 5.3538214809162710e-01
    -6.9252569636958672e-01 -5.3484462200721165e-02
    3.7549057350434782e-02 -4.1803198983676314e-02
    -8.0776998619121482e-03 5.3536326835208381e-01
    -6.9250915395561918e-01 -5.3454864609456934e-02
    3.7513093507601888e-02 -4.1802600030582483e-02
    -8.0761750900249386e-03 5.3539465745589887e-01
    -6.9249364439861127e-01 -5.3500925182161728e-02
    3.7493154347030225e-02 -4.1800688153842094e-02
    -8.0794175971379157e-03 5.3536919717406983e-01</data></extrinsic_parameters>
<image_points type_id="opencv-matrix">
  <rows>25</rows>
  <cols>54</cols>
  <dt>"2f"</dt>
  <data>
    6.24289673e+02 8.47209595e+02 7.18611633e+02 8.52776367e+02
    8.12348145e+02 8.57760315e+02 9.07314270e+02 8.62023193e+02
    1.00130328e+03 8.66691467e+02 1.09543054e+03 8.70785828e+02
    1.18970532e+03 8.74366577e+02 1.28400793e+03 8.77166687e+02
    1.37791675e+03 8.79403503e+02 6.18013000e+02 9.18611023e+02
    7.13432678e+02 9.24121521e+02 8.08724792e+02 9.28741638e+02
    9.04803467e+02 9.34017395e+02 1.00035895e+03 9.38066650e+02
    1.09559497e+03 9.41825928e+02 1.19156958e+03 9.45791321e+02
    1.28689954e+03 9.48945007e+02 1.38197986e+03 9.51838135e+02
    6.11151733e+02 9.90825256e+02 7.08087463e+02 9.96619324e+02
    8.04528931e+02 1.00183014e+03 9.02375916e+02 1.00666876e+03
    9.99028564e+02 1.01090607e+03 1.09613416e+03 1.01460968e+03
    1.19315649e+03 1.01846667e+03 1.28995032e+03 1.02181964e+03
    1.38637476e+03 1.02485669e+03 6.04439026e+02 1.06575378e+03
    7.02717529e+02 1.07118896e+03 8.00685608e+02 1.07663928e+03
    8.99762695e+02 1.08140540e+03 9.98147461e+02 1.08608838e+03
    1.09625806e+03 1.09029333e+03 1.19500427e+03 1.09392285e+03
    1.29312488e+03 1.09738196e+03 1.39098645e+03 1.10034778e+03
    5.97322144e+02 1.14148889e+03 6.97237732e+02 1.14721960e+03
    7.96724060e+02 1.15274976e+03 8.97268372e+02 1.15754407e+03
    9.96919373e+02 1.16191138e+03 1.09652832e+03 1.16645276e+03
    1.19661951e+03 1.17031860e+03 1.29628357e+03 1.17385437e+03
    1.39544580e+03 1.17671277e+03 5.90150391e+02 1.21850232e+03
    6.91595947e+02 1.22504736e+03 7.92422119e+02 1.23072510e+03
    8.94506226e+02 1.23586853e+03 9.95675720e+02 1.24052930e+03
    1.09694495e+03 1.24493298e+03 1.19853894e+03 1.24874268e+03
    1.29960522e+03 1.25231824e+03 1.40028882e+03 1.25522449e+03
    6.24321533e+02 8.47259644e+02 7.18696838e+02 8.52816956e+02
    8.12492065e+02 8.57880005e+02 9.07398438e+02 8.62138550e+02
    1.00133173e+03 8.66797852e+02 1.09543945e+03 8.70870422e+02
    1.18978162e+03 8.74424500e+02 1.28409021e+03 8.77233643e+02
    1.37795068e+03 8.79473633e+02 6.18061951e+02 9.18664551e+02
    7.13485352e+02 9.24202698e+02 8.08803894e+02 9.28773499e+02
    9.04836853e+02 9.34091431e+02 1.00036438e+03 9.38133972e+02
    1.09560339e+03 9.41908264e+02 1.19160449e+03 9.45866577e+02
    1.28692322e+03 9.48992126e+02 1.38202405e+03 9.51959595e+02
    6.11234863e+02 9.90840393e+02 7.08191589e+02 9.96590637e+02
    8.04640503e+02 1.00189844e+03 9.02421143e+02 1.00675195e+03
    9.99102356e+02 1.01094385e+03 1.09613831e+03 1.01465918e+03
    1.19324365e+03 1.01851697e+03 1.28994312e+03 1.02192749e+03
    1.38639514e+03 1.02490393e+03 6.04476807e+02 1.06581018e+03
    7.02754333e+02 1.07121545e+03 8.00704163e+02 1.07667566e+03
    8.99865540e+02 1.08147021e+03 9.98196472e+02 1.08609155e+03
    1.09634473e+03 1.09035559e+03 1.19502490e+03 1.09397754e+03
    1.29319165e+03 1.09743274e+03 1.39102356e+03 1.10040576e+03
    5.97374817e+02 1.14150732e+03 6.97408630e+02 1.14732288e+03
    7.96771179e+02 1.15282141e+03 8.97268127e+02 1.15762793e+03
    9.96962402e+02 1.16192871e+03 1.09659717e+03 1.16649805e+03
    1.19667981e+03 1.17043225e+03 1.29638513e+03 1.17397827e+03
    1.39552991e+03 1.17673401e+03 5.90227539e+02 1.21857129e+03
    6.91640076e+02 1.22504517e+03 7.92509216e+02 1.23078723e+03
    8.94541260e+02 1.23597241e+03 9.95728882e+02 1.24055627e+03
    1.09703174e+03 1.24500476e+03 1.19864038e+03 1.24880359e+03
    1.29964136e+03 1.25232861e+03 1.40034216e+03 1.25534314e+03
    6.24344116e+02 8.47317688e+02 7.18660095e+02 8.52849670e+02
    8.12466553e+02 8.57908997e+02 9.07404785e+02 8.62146240e+02
    1.00135229e+03 8.66808228e+02 1.09550146e+03 8.70904724e+02
    1.18976062e+03 8.74417969e+02 1.28414648e+03 8.77262756e+02
    1.37794702e+03 8.79503784e+02 6.18060181e+02 9.18728271e+02
    7.13481445e+02 9.24239197e+02 8.08829712e+02 9.28855286e+02
    9.04890259e+02 9.34096375e+02 1.00038281e+03 9.38204712e+02
    1.09563550e+03 9.41975220e+02 1.19161157e+03 9.45826294e+02
    1.28697156e+03 9.49005371e+02 1.38209009e+03 9.51988586e+02
    6.11295471e+02 9.90890808e+02 7.08216370e+02 9.96685059e+02
    8.04609436e+02 1.00198364e+03 9.02435669e+02 1.00680145e+03
    9.99131287e+02 1.01100562e+03 1.09620874e+03 1.01468414e+03
    1.19322632e+03 1.01861816e+03 1.28992310e+03 1.02189673e+03
    1.38641150e+03 1.02491931e+03 6.04498535e+02 1.06587085e+03
    7.02748169e+02 1.07131079e+03 8.00729187e+02 1.07677148e+03
    8.99858521e+02 1.08154004e+03 9.98223022e+02 1.08616504e+03
    1.09633069e+03 1.09037720e+03 1.19506262e+03 1.09409119e+03
    1.29320129e+03 1.09746655e+03 1.39109351e+03 1.10049390e+03
    5.97391541e+02 1.14160156e+03 6.97426636e+02 1.14737488e+03
    7.96769897e+02 1.15284668e+03 8.97300171e+02 1.15765686e+03
    9.96976318e+02 1.16198560e+03 1.09662268e+03 1.16651404e+03
    1.19664600e+03 1.17047815e+03 1.29638977e+03 1.17400415e+03
    1.39553528e+03 1.17677698e+03 5.90230774e+02 1.21857971e+03
    6.91634644e+02 1.22510791e+03 7.92467041e+02 1.23082715e+03
    8.94550171e+02 1.23602625e+03 9.95753967e+02 1.24067102e+03
    1.09700122e+03 1.24498376e+03 1.19862317e+03 1.24888721e+03
    1.29967969e+03 1.25242273e+03 1.40033032e+03 1.25536938e+03
    6.24339539e+02 8.47275391e+02 7.18697266e+02 8.52838806e+02
    8.12462708e+02 8.57874695e+02 9.07385620e+02 8.62117920e+02
    1.00134784e+03 8.66736755e+02 1.09549854e+03 8.70928772e+02
    1.18977051e+03 8.74387207e+02 1.28405640e+03 8.77246582e+02
    1.37798511e+03 8.79464844e+02 6.18040771e+02 9.18662170e+02
    7.13474670e+02 9.24271667e+02 8.08782410e+02 9.28783691e+02
    9.04834900e+02 9.34054382e+02 1.00040070e+03 9.38166687e+02
    1.09562146e+03 9.41960754e+02 1.19159583e+03 9.45813721e+02
    1.28695959e+03 9.49036743e+02 1.38202954e+03 9.51848816e+02
    6.11286926e+02 9.90802185e+02 7.08210876e+02 9.96664856e+02
    8.04596619e+02 1.00188672e+03 9.02445435e+02 1.00672900e+03
    9.99077148e+02 1.01096588e+03 1.09620483e+03 1.01466144e+03
    1.19322070e+03 1.01854492e+03 1.28993652e+03 1.02191138e+03
    1.38640417e+03 1.02490295e+03 6.04451355e+02 1.06584216e+03
    7.02754150e+02 1.07131177e+03 8.00727722e+02 1.07673120e+03
    8.99841980e+02 1.08149390e+03 9.98208801e+02 1.08613867e+03
    1.09634436e+03 1.09035645e+03 1.19505945e+03 1.09401611e+03
    1.29318628e+03 1.09744910e+03 1.39107080e+03 1.10047302e+03
    5.97411377e+02 1.14151929e+03 6.97349915e+02 1.14740454e+03
    7.96784058e+02 1.15279114e+03 8.97285339e+02 1.15764624e+03
    9.96976257e+02 1.16193860e+03 1.09658191e+03 1.16654749e+03
    1.19664490e+03 1.17043713e+03 1.29638940e+03 1.17398584e+03
    1.39548389e+03 1.17675269e+03 5.90208374e+02 1.21858252e+03
    6.91614685e+02 1.22506738e+03 7.92484497e+02 1.23079150e+03
    8.94560791e+02 1.23595972e+03 9.95750366e+02 1.24059216e+03
    1.09703467e+03 1.24499341e+03 1.19860718e+03 1.24882349e+03
    1.29966028e+03 1.25236133e+03 1.40031665e+03 1.25530786e+03
    6.27911987e+02 8.63866760e+02 7.22927307e+02 8.68795715e+02
    8.17333191e+02 8.73245239e+02 9.12829956e+02 8.76822021e+02
    1.00723090e+03 8.80869385e+02 1.10181323e+03 8.84337891e+02
    1.19649524e+03 8.87040161e+02 1.29107458e+03 8.89128479e+02
    1.38525330e+03 8.90569580e+02 6.23485596e+02 9.30907959e+02
    7.19549683e+02 9.35719604e+02 8.15792175e+02 9.39812988e+02
    9.12387146e+02 9.44497375e+02 1.00859802e+03 9.47952576e+02
    1.10432922e+03 9.50932861e+02 1.20083911e+03 9.54193604e+02
    1.29652600e+03 9.56651672e+02 1.39201868e+03 9.58660522e+02
    6.18486450e+02 9.98532471e+02 7.16355103e+02 1.00380493e+03
    8.13523743e+02 1.00853699e+03 9.12257996e+02 1.01275531e+03
    1.00962573e+03 1.01632629e+03 1.10731677e+03 1.01926849e+03
    1.20498828e+03 1.02239929e+03 1.30223083e+03 1.02506104e+03
    1.39910181e+03 1.02725964e+03 6.13614746e+02 1.06887341e+03
    7.12934631e+02 1.07389551e+03 8.11866760e+02 1.07875879e+03
    9.11906189e+02 1.08294763e+03 1.01114539e+03 1.08698035e+03
    1.11008582e+03 1.09031348e+03 1.20943677e+03 1.09339160e+03
    1.30827258e+03 1.09600977e+03 1.40662964e+03 1.09824097e+03
    6.08435547e+02 1.14012341e+03 7.09623291e+02 1.14527087e+03
    8.10074585e+02 1.15024780e+03 9.11722961e+02 1.15439502e+03
    1.01241412e+03 1.15794189e+03 1.11289209e+03 1.16189795e+03
    1.21379370e+03 1.16507178e+03 1.31422339e+03 1.16794226e+03
    1.41417798e+03 1.16994690e+03 6.03235657e+02 1.21197339e+03
    7.06043274e+02 1.21796826e+03 8.08127625e+02 1.22324475e+03
    9.11513855e+02 1.22783801e+03 1.01375134e+03 1.23197681e+03
    1.11624194e+03 1.23561670e+03 1.21857007e+03 1.23880981e+03
    1.32058826e+03 1.24156104e+03 1.42201184e+03 1.24370410e+03
    6.75578796e+02 4.34557007e+02 7.71882751e+02 4.39139526e+02
    8.67426331e+02 4.43302460e+02 9.64008789e+02 4.47534485e+02
    1.05947839e+03 4.51766907e+02 1.15498901e+03 4.56121979e+02
    1.25052759e+03 4.60116516e+02 1.34587671e+03 4.64090424e+02
    1.44080737e+03 4.67970642e+02 6.71561951e+02 5.32971558e+02
    7.67923035e+02 5.37233276e+02 8.64044373e+02 5.41354919e+02
    9.60672058e+02 5.45714783e+02 1.05668494e+03 5.49685425e+02
    1.15222815e+03 5.53517029e+02 1.24828479e+03 5.57651917e+02
    1.34357971e+03 5.61586304e+02 1.43858948e+03 5.65403564e+02
    6.67626526e+02 6.31308777e+02 7.64225342e+02 6.35654175e+02
    8.60419067e+02 6.39695984e+02 9.57432190e+02 6.43706299e+02
    1.05351111e+03 6.47587524e+02 1.14970154e+03 6.51414001e+02
    1.24575635e+03 6.55200256e+02 1.34141931e+03 6.59052856e+02
    1.43666187e+03 6.62755859e+02 6.63699768e+02 7.31284485e+02
    7.60668396e+02 7.35101746e+02 8.56990662e+02 7.39272217e+02
    9.54363403e+02 7.42945984e+02 1.05075562e+03 7.46848633e+02
    1.14693347e+03 7.50597473e+02 1.24350012e+03 7.54410095e+02
    1.33926453e+03 7.57855835e+02 1.43461719e+03 7.61445618e+02
    6.59804321e+02 8.30568909e+02 7.57197815e+02 8.34373718e+02
    8.53745544e+02 8.38131226e+02 9.51303406e+02 8.42033447e+02
    1.04793738e+03 8.45446777e+02 1.14434216e+03 8.49221497e+02
    1.24091113e+03 8.52766785e+02 1.33717993e+03 8.56303833e+02
    1.43267761e+03 8.59404053e+02 6.56084351e+02 9.30278015e+02
    7.53648010e+02 9.34035706e+02 8.50470947e+02 9.37992310e+02
    9.48196045e+02 9.41537537e+02 1.04510022e+03 9.45163391e+02
    1.14170276e+03 9.48485229e+02 1.23862451e+03 9.51734985e+02
    1.33494702e+03 9.55049377e+02 1.43068726e+03 9.58235718e+02
    3.00714661e+02 3.48119659e+02 3.97212616e+02 3.48310303e+02
    4.92985992e+02 3.48283875e+02 5.89774597e+02 3.48245422e+02
    6.85478149e+02 3.48254791e+02 7.81293762e+02 3.48480103e+02
    8.77122009e+02 3.48427368e+02 9.72731323e+02 3.48423828e+02
    1.06800879e+03 3.48440643e+02 3.00961395e+02 4.47341248e+02
    3.97262421e+02 4.47285370e+02 4.93312500e+02 4.47175568e+02
    5.90016602e+02 4.47175385e+02 6.86033813e+02 4.46927551e+02
    7.81591858e+02 4.46686798e+02 8.77783936e+02 4.46632721e+02
    9.73257812e+02 4.46682770e+02 1.06844727e+03 4.46616882e+02
    3.01136871e+02 5.46086121e+02 3.97592010e+02 5.45995850e+02
    4.93504242e+02 5.45770325e+02 5.90427002e+02 5.45494873e+02
    6.86247070e+02 5.45343445e+02 7.82243530e+02 5.45030762e+02
    8.78331299e+02 5.44732056e+02 9.73813293e+02 5.44618652e+02
    1.06905029e+03 5.44329529e+02 3.01550598e+02 6.46116150e+02
    3.98041656e+02 6.45598816e+02 4.93913971e+02 6.45462402e+02
    5.90856079e+02 6.44906372e+02 6.86906921e+02 6.44669922e+02
    7.82700562e+02 6.44307190e+02 8.79072327e+02 6.44033997e+02
    9.74522339e+02 6.43443848e+02 1.06962585e+03 6.43186584e+02
    3.01807922e+02 7.45243835e+02 3.98656860e+02 7.44669067e+02
    4.94549011e+02 7.44126099e+02 5.91462097e+02 7.43780945e+02
    6.87392883e+02 7.43086609e+02 7.83278381e+02 7.42669434e+02
    8.79363647e+02 7.42176758e+02 9.75111145e+02 7.41633484e+02
    1.07013794e+03 7.40880981e+02 3.02280731e+02 8.44511658e+02
    3.99108887e+02 8.43819580e+02 4.95047058e+02 8.43442505e+02
    5.91919983e+02 8.42756409e+02 6.87978149e+02 8.42187805e+02
    7.83917297e+02 8.41363770e+02 8.80052124e+02 8.40497925e+02
    9.75646484e+02 8.39866943e+02 1.07070374e+03 8.39072327e+02
    2.21862686e+02 8.69685974e+02 3.22802399e+02 8.67293030e+02
    4.23065857e+02 8.64528809e+02 5.24274170e+02 8.61246338e+02
    6.24580750e+02 8.58276611e+02 7.24716431e+02 8.55074219e+02
    8.25043579e+02 8.51457703e+02 9.25094360e+02 8.47377380e+02
    1.02469861e+03 8.43135681e+02 2.22867096e+02 9.68290833e+02
    3.24244507e+02 9.65541199e+02 4.25553406e+02 9.62489014e+02
    5.27407410e+02 9.59607910e+02 6.28575745e+02 9.56119019e+02
    7.29338562e+02 9.52398132e+02 8.30646667e+02 9.48893066e+02
    9.31303162e+02 9.45079102e+02 1.03138452e+03 9.40837708e+02
    2.23768753e+02 1.06734497e+03 3.26028046e+02 1.06468250e+03
    4.27812714e+02 1.06175891e+03 5.30730164e+02 1.05847095e+03
    6.32409180e+02 1.05498230e+03 7.34290833e+02 1.05103345e+03
    8.36136047e+02 1.04729578e+03 9.37556152e+02 1.04325281e+03
    1.03842468e+03 1.03894580e+03 2.24850479e+02 1.16897302e+03
    3.28024323e+02 1.16580396e+03 4.30477173e+02 1.16284546e+03
    5.34049866e+02 1.15926196e+03 6.36696106e+02 1.15578027e+03
    7.39159363e+02 1.15201758e+03 8.41975952e+02 1.14806030e+03
    9.43933105e+02 1.14366785e+03 1.04561841e+03 1.13931396e+03
    2.25852036e+02 1.27061731e+03 3.30137909e+02 1.26743689e+03
    4.33422974e+02 1.26419385e+03 5.37556396e+02 1.26066858e+03
    6.40893005e+02 1.25676941e+03 7.44164429e+02 1.25300684e+03
    8.47467041e+02 1.24883008e+03 9.50442688e+02 1.24453345e+03
    1.05265527e+03 1.23971436e+03 2.26955551e+02 1.37373523e+03
    3.32095032e+02 1.37054163e+03 4.35994873e+02 1.36742639e+03
    5.41093933e+02 1.36365771e+03 6.45351501e+02 1.35972156e+03
    7.49313049e+02 1.35562976e+03 8.53354126e+02 1.35110583e+03
    9.57022766e+02 1.34660535e+03 1.05998596e+03 1.34175854e+03
    6.52036316e+02 1.04136253e+02 7.51498718e+02 9.92791367e+01
    8.50297241e+02 9.41024017e+01 9.50244568e+02 8.93387070e+01
    1.04898132e+03 8.43053207e+01 1.14775366e+03 7.99114990e+01
    1.24658777e+03 7.52118683e+01 1.34533838e+03 7.08814240e+01
    1.44364185e+03 6.65240402e+01 6.58026611e+02 2.06943192e+02
    7.56991821e+02 2.01550812e+02 8.55831604e+02 1.96733353e+02
    9.55183105e+02 1.91711731e+02 1.05405176e+03 1.86866211e+02
    1.15229297e+03 1.81931427e+02 1.25117896e+03 1.77415100e+02
    1.34931824e+03 1.72947174e+02 1.44717676e+03 1.68578339e+02
    6.63684448e+02 3.08681213e+02 7.62484009e+02 3.03578705e+02
    8.60952209e+02 2.98389740e+02 9.60268372e+02 2.93330780e+02
    1.05857007e+03 2.88470551e+02 1.15694263e+03 2.83538055e+02
    1.25540198e+03 2.78656403e+02 1.35326245e+03 2.74110443e+02
    1.45090063e+03 2.69422394e+02 6.69456665e+02 4.11237213e+02
    7.68185120e+02 4.05645416e+02 8.66185974e+02 4.00707062e+02
    9.65335388e+02 3.95287689e+02 1.06342712e+03 3.90424072e+02
    1.16133960e+03 3.85464935e+02 1.25974084e+03 3.80801727e+02
    1.35719214e+03 3.75702637e+02 1.45440942e+03 3.71209290e+02
    6.74971252e+02 5.12267029e+02 7.73674255e+02 5.06805450e+02
    8.71398254e+02 5.01272461e+02 9.70115112e+02 4.96403412e+02
    1.06799475e+03 4.91063477e+02 1.16558386e+03 4.86087128e+02
    1.26349939e+03 4.81035400e+02 1.36088977e+03 4.76192108e+02
    1.45782483e+03 4.71011444e+02 6.80525452e+02 6.13133606e+02
    7.78815979e+02 6.07425537e+02 8.76356445e+02 6.02255920e+02
    9.74750977e+02 5.96850220e+02 1.07243542e+03 5.91745911e+02
    1.16981519e+03 5.86375061e+02 1.26732788e+03 5.81104309e+02
    1.36450684e+03 5.76154175e+02 1.46092407e+03 5.70856812e+02
    7.62591248e+02 1.33878220e+02 8.59579346e+02 1.37071304e+02
    9.55774719e+02 1.40025284e+02 1.05281030e+03 1.43256195e+02
    1.14846399e+03 1.46291412e+02 1.24397571e+03 1.49801208e+02
    1.33938953e+03 1.53056824e+02 1.43453638e+03 1.56460724e+02
    1.52902771e+03 1.59777023e+02 7.60008545e+02 2.34574265e+02
    8.56646484e+02 2.37256470e+02 9.52995239e+02 2.40275406e+02
    1.04959351e+03 2.43243942e+02 1.14541675e+03 2.46117126e+02
    1.24072327e+03 2.49038437e+02 1.33623450e+03 2.52206329e+02
    1.43076355e+03 2.55386581e+02 1.52501367e+03 2.58541870e+02
    7.57309692e+02 3.34465912e+02 8.53871521e+02 3.37260193e+02
    9.49945679e+02 3.39810303e+02 1.04665930e+03 3.42474365e+02
    1.14215430e+03 3.45224548e+02 1.23755872e+03 3.47964996e+02
    1.33282678e+03 3.50791809e+02 1.42726233e+03 3.53758362e+02
    1.52135388e+03 3.56626526e+02 7.54772644e+02 4.35536804e+02
    8.51422180e+02 4.37619781e+02 9.47115784e+02 4.40252014e+02
    1.04372009e+03 4.42503357e+02 1.13920459e+03 4.45089020e+02
    1.23428552e+03 4.47569641e+02 1.32962683e+03 4.50411377e+02
    1.42378931e+03 4.52721497e+02 1.51760059e+03 4.55543579e+02
    7.52266418e+02 5.35242798e+02 8.48896423e+02 5.37282532e+02
    9.44503418e+02 5.39196960e+02 1.04089026e+03 5.41653137e+02
    1.13623169e+03 5.43706970e+02 1.23108936e+03 5.46111755e+02
    1.32604236e+03 5.48450684e+02 1.42035217e+03 5.50901428e+02
    1.51391052e+03 5.52993835e+02 7.49914856e+02 6.35003906e+02
    8.46288025e+02 6.36681091e+02 9.41781799e+02 6.38753601e+02
    1.03799182e+03 6.40600281e+02 1.13316614e+03 6.42714600e+02
    1.22787109e+03 6.44610901e+02 1.32263928e+03 6.46487061e+02
    1.41681860e+03 6.48704773e+02 1.51024072e+03 6.50717468e+02
    1.18814819e+03 2.57360783e+01 1.23417371e+03 1.23361435e+02
    1.28133105e+03 2.18278824e+02 1.32780579e+03 3.15303955e+02
    1.37332300e+03 4.08414673e+02 1.41873840e+03 5.02749023e+02
    1.46353467e+03 5.95349060e+02 1.50789795e+03 6.86967224e+02
    1.55164233e+03 7.77916504e+02 1.08644800e+03 7.86469650e+01
    1.13502869e+03 1.74120132e+02 1.18178955e+03 2.70833801e+02
    1.22852698e+03 3.65167603e+02 1.27532666e+03 4.60151215e+02
    1.32104700e+03 5.53224243e+02 1.36665198e+03 6.45691101e+02
    1.41132336e+03 7.37381592e+02 1.45546765e+03 8.27542358e+02
    9.87038330e+02 1.29359726e+02 1.03427820e+03 2.26083557e+02
    1.08265393e+03 3.21374634e+02 1.13020911e+03 4.17230316e+02
    1.17719421e+03 5.11158264e+02 1.22371985e+03 6.03902466e+02
    1.26977539e+03 6.96754395e+02 1.31509692e+03 7.87771057e+02
    1.35982703e+03 8.77442017e+02 8.84736511e+02 1.82454269e+02
    9.34308350e+02 2.78826782e+02 9.82319580e+02 3.74025330e+02
    1.03072205e+03 4.69007355e+02 1.07820911e+03 5.63080627e+02
    1.12526843e+03 6.55808899e+02 1.17193225e+03 7.48123352e+02
    1.21804089e+03 8.38579773e+02 1.26305981e+03 9.27900391e+02
    7.84927917e+02 2.34988678e+02 8.34084778e+02 3.31570129e+02
    8.83396301e+02 4.26177856e+02 9.31836487e+02 5.21568115e+02
    9.80285217e+02 6.14811829e+02 1.02762183e+03 7.06924866e+02
    1.07484253e+03 7.98703369e+02 1.12131299e+03 8.88872437e+02
    1.16743835e+03 9.77832153e+02 6.83489197e+02 2.88406372e+02
    7.34543518e+02 3.84346008e+02 7.83256165e+02 4.79086395e+02
    8.32908203e+02 5.73715515e+02 8.81538147e+02 6.66753723e+02
    9.29756714e+02 7.58453369e+02 9.77628601e+02 8.49540588e+02
    1.02477051e+03 9.39453857e+02 1.07124084e+03 1.02798804e+03
    1.65896033e+03 2.61370453e+02 1.64380591e+03 3.58912628e+02
    1.62925610e+03 4.54356110e+02 1.61484924e+03 5.49350464e+02
    1.60065710e+03 6.41635559e+02 1.58664551e+03 7.32527527e+02
    1.57300183e+03 8.22322937e+02 1.55981628e+03 9.10760620e+02
    1.54679919e+03 9.97680237e+02 1.54837939e+03 2.53704849e+02
    1.53455908e+03 3.51301025e+02 1.52099133e+03 4.47413849e+02
    1.50734155e+03 5.42163086e+02 1.49446960e+03 6.35121582e+02
    1.48161780e+03 7.26336975e+02 1.46898828e+03 8.16151611e+02
    1.45667810e+03 9.04615479e+02 1.44458240e+03 9.91061279e+02
    1.43799231e+03 2.46438263e+02 1.42496436e+03 3.44096924e+02
    1.41244873e+03 4.40217346e+02 1.40012183e+03 5.35509705e+02
    1.38813782e+03 6.28667542e+02 1.37644250e+03 7.20302429e+02
    1.36485608e+03 8.10530579e+02 1.35346082e+03 8.98740967e+02
    1.34243091e+03 9.85635742e+02 1.32565381e+03 2.39153473e+02
    1.31411157e+03 3.37766876e+02 1.30259900e+03 4.33633087e+02
    1.29149316e+03 5.29525635e+02 1.28041846e+03 6.22551819e+02
    1.26961841e+03 7.14168396e+02 1.25911841e+03 8.04713318e+02
    1.24905432e+03 8.93295288e+02 1.23888501e+03 9.79904724e+02
    1.21393958e+03 2.32810150e+02 1.20360254e+03 3.31261932e+02
    1.19336353e+03 4.27751282e+02 1.18319299e+03 5.23404541e+02
    1.17331799e+03 6.17085938e+02 1.16365649e+03 7.08591370e+02
    1.15418127e+03 7.99107727e+02 1.14483997e+03 8.87735413e+02
    1.13614233e+03 9.74854980e+02 1.10180835e+03 2.26698532e+02
    1.09248242e+03 3.25352051e+02 1.08307458e+03 4.21845032e+02
    1.07419543e+03 5.17796997e+02 1.06537073e+03 6.11377747e+02
    1.05704504e+03 7.03142761e+02 1.04865588e+03 7.93748901e+02
    1.04049561e+03 8.82689514e+02 1.03250500e+03 9.69635742e+02
    7.18112411e+01 3.46457886e+02 1.68855118e+02 3.49125580e+02
    2.65649719e+02 3.51529846e+02 3.63442169e+02 3.54260864e+02
    4.60520508e+02 3.56842712e+02 5.57863770e+02 3.59695526e+02
    6.55430603e+02 3.62435486e+02 7.53094421e+02 3.65207611e+02
    8.50422058e+02 3.68182190e+02 7.01587830e+01 4.46732605e+02
    1.66952911e+02 4.49181152e+02 2.63571228e+02 4.51887360e+02
    3.61277466e+02 4.54523102e+02 4.58342865e+02 4.57125061e+02
    5.55362366e+02 4.59632141e+02 6.53160278e+02 4.62480408e+02
    7.50323730e+02 4.65374969e+02 8.47481140e+02 4.68171875e+02
    6.83949890e+01 5.46269104e+02 1.65131790e+02 5.48942139e+02
    2.61510651e+02 5.51467896e+02 3.59214783e+02 5.54024658e+02
    4.55927551e+02 5.56715271e+02 5.53093262e+02 5.59339722e+02
    6.50481750e+02 5.61958679e+02 7.47621399e+02 5.64799805e+02
    8.44709534e+02 5.67418701e+02 6.67930832e+01 6.46715332e+02
    1.63400543e+02 6.49072998e+02 2.59543884e+02 6.51870911e+02
    3.57006531e+02 6.54183105e+02 4.53827972e+02 6.56948792e+02
    5.50652039e+02 6.59448730e+02 6.48155823e+02 6.62368164e+02
    7.45053650e+02 6.64773071e+02 8.41776794e+02 6.67625305e+02
    6.52084045e+01 7.45907104e+02 1.61915924e+02 7.48416565e+02
    2.57913666e+02 7.50691162e+02 3.54965149e+02 7.53495422e+02
    4.51565735e+02 7.55954041e+02 5.48274292e+02 7.58518250e+02
    6.45286865e+02 7.61160889e+02 7.42324524e+02 7.63837219e+02
    8.38885437e+02 7.66284241e+02 6.34379959e+01 8.45119446e+02
    1.60010284e+02 8.47355103e+02 2.56014709e+02 8.50129944e+02
    3.52920288e+02 8.52479309e+02 4.49417480e+02 8.55132385e+02
    5.45930908e+02 8.57522400e+02 6.42909363e+02 8.59911926e+02
    7.39593262e+02 8.62599243e+02 8.36066101e+02 8.65158020e+02
    6.86469421e+02 2.54853561e+02 7.81815002e+02 2.56544342e+02
    8.76513062e+02 2.57976929e+02 9.72252014e+02 2.59703369e+02
    1.06686316e+03 2.61327301e+02 1.16156018e+03 2.63333405e+02
    1.25621350e+03 2.65190948e+02 1.35082666e+03 2.67100037e+02
    1.44499951e+03 2.69111572e+02 6.85210083e+02 3.53231110e+02
    7.80238831e+02 3.54608917e+02 8.75041260e+02 3.56194397e+02
    9.70359131e+02 3.57708862e+02 1.06509802e+03 3.59275848e+02
    1.15939612e+03 3.60817169e+02 1.25416602e+03 3.62679382e+02
    1.34831934e+03 3.64579620e+02 1.44211780e+03 3.66406616e+02
    6.83904419e+02 4.50799866e+02 7.78720764e+02 4.52266113e+02
    8.73220459e+02 4.53532166e+02 9.68645569e+02 4.55045593e+02
    1.06302625e+03 4.56490234e+02 1.15743591e+03 4.58055115e+02
    1.25187000e+03 4.59584778e+02 1.34587451e+03 4.61307220e+02
    1.43955762e+03 4.62992279e+02 6.82658386e+02 5.49307739e+02
    7.77448669e+02 5.50391479e+02 8.71658020e+02 5.51827087e+02
    9.66907288e+02 5.52893616e+02 1.06117700e+03 5.54368713e+02
    1.15533203e+03 5.55705627e+02 1.24980432e+03 5.57336487e+02
    1.34354919e+03 5.58601379e+02 1.43680920e+03 5.60274902e+02
    6.81424683e+02 6.46568420e+02 7.76349365e+02 6.47571167e+02
    8.70292542e+02 6.48570007e+02 9.65238281e+02 6.49947998e+02
    1.05930017e+03 6.50993652e+02 1.15321118e+03 6.52309448e+02
    1.24730481e+03 6.53562134e+02 1.34107642e+03 6.55058777e+02
    1.43416284e+03 6.56266724e+02 6.80295776e+02 7.43785767e+02
    7.74798218e+02 7.44539307e+02 8.68605591e+02 7.45661377e+02
    9.63501648e+02 7.46601685e+02 1.05736987e+03 7.47836792e+02
    1.15116931e+03 7.48732422e+02 1.24503601e+03 7.49737793e+02
    1.33851465e+03 7.51043640e+02 1.43148669e+03 7.52244446e+02
    6.68872131e+02 2.56628632e+02 7.64243591e+02 2.58721893e+02
    8.58927917e+02 2.60674225e+02 9.54603088e+02 2.62759583e+02
    1.04934534e+03 2.64804108e+02 1.14417749e+03 2.67291016e+02
    1.23899207e+03 2.69452820e+02 1.33381116e+03 2.71854401e+02
    1.42817908e+03 2.74259705e+02 6.67263489e+02 3.54927704e+02
    7.62173523e+02 3.56703705e+02 8.56965027e+02 3.58745514e+02
    9.52405090e+02 3.60787323e+02 1.04720618e+03 3.62824554e+02
    1.14156799e+03 3.64871613e+02 1.23663599e+03 3.67139923e+02
    1.33088428e+03 3.69383881e+02 1.42497095e+03 3.71648468e+02
    6.65552185e+02 4.52434448e+02 7.60324280e+02 4.54401794e+02
    8.54849976e+02 4.56238922e+02 9.50315125e+02 4.58049896e+02
    1.04471887e+03 4.60136536e+02 1.13932153e+03 4.62100800e+02
    1.23398035e+03 4.64123535e+02 1.32826160e+03 4.66295288e+02
    1.42211670e+03 4.68368561e+02 6.63819397e+02 5.50992126e+02
    7.58645508e+02 5.52496155e+02 8.52791748e+02 5.54470825e+02
    9.48156616e+02 5.56089111e+02 1.04264343e+03 5.58082092e+02
    1.13676721e+03 5.59890015e+02 1.23152966e+03 5.61995178e+02
    1.32548999e+03 5.63693604e+02 1.41913525e+03 5.65950317e+02
    6.62203796e+02 6.48333923e+02 7.57024719e+02 6.49744751e+02
    8.51054932e+02 6.51196838e+02 9.46105896e+02 6.53143311e+02
    1.04032361e+03 6.54762146e+02 1.13430725e+03 6.56633118e+02
    1.22862146e+03 6.58378479e+02 1.32261694e+03 6.60382202e+02
    1.41605896e+03 6.62100403e+02 6.60509705e+02 7.45515259e+02
    7.55100708e+02 7.46811890e+02 8.49082031e+02 7.48481873e+02
    9.43937988e+02 7.49995422e+02 1.03798389e+03 7.51715759e+02
    1.13191418e+03 7.53198608e+02 1.22608521e+03 7.54777832e+02
    1.31979736e+03 7.56558533e+02 1.41304211e+03 7.58273865e+02
    6.73484985e+02 5.23725708e+02 7.70295959e+02 5.29936951e+02
    8.66563660e+02 5.35811279e+02 9.63892273e+02 5.41533875e+02
    1.06025659e+03 5.47286194e+02 1.15665503e+03 5.53159485e+02
    1.25316992e+03 5.58532166e+02 1.34950818e+03 5.63699158e+02
    1.44552161e+03 5.68620056e+02 6.67329407e+02 6.20052429e+02
    7.64399048e+02 6.26149292e+02 8.61408264e+02 6.31896851e+02
    9.59067139e+02 6.37910156e+02 1.05612903e+03 6.43472473e+02
    1.15288660e+03 6.48810425e+02 1.25014233e+03 6.54408691e+02
    1.34686353e+03 6.59672241e+02 1.44315442e+03 6.64782410e+02
    6.60941040e+02 7.16665405e+02 7.58581299e+02 7.22858337e+02
    8.55982178e+02 7.28872070e+02 9.54429871e+02 7.34515198e+02
    1.05172424e+03 7.40113708e+02 1.14932129e+03 7.45393677e+02
    1.24695471e+03 7.50748413e+02 1.34424231e+03 7.56121338e+02
    1.44108508e+03 7.61074646e+02 6.54606812e+02 8.15368835e+02
    7.52921143e+02 8.21141602e+02 8.50669312e+02 8.27182251e+02
    9.49533325e+02 8.32749512e+02 1.04757068e+03 8.38378662e+02
    1.14550525e+03 8.43829529e+02 1.24384875e+03 8.49276184e+02
    1.34151245e+03 8.54212646e+02 1.43876172e+03 8.59331360e+02
    6.48209900e+02 9.13845154e+02 7.47314514e+02 9.19740173e+02
    8.45545471e+02 9.25437073e+02 9.44862427e+02 9.31246155e+02
    1.04334106e+03 9.36604492e+02 1.14174780e+03 9.42076660e+02
    1.24038452e+03 9.47309387e+02 1.33868408e+03 9.52515747e+02
    1.43654688e+03 9.57130859e+02 6.41813171e+02 1.01318713e+03
    7.41351196e+02 1.01918176e+03 8.40141724e+02 1.02517139e+03
    9.39929993e+02 1.03075452e+03 1.03903931e+03 1.03627966e+03
    1.13803723e+03 1.04147620e+03 1.23714282e+03 1.04653564e+03
    1.33583691e+03 1.05159155e+03 1.43423938e+03 1.05641455e+03
    6.21498901e+02 6.42335938e+02 7.20631775e+02 6.48199280e+02
    8.19199219e+02 6.53805237e+02 9.19020447e+02 6.59049438e+02
    1.01769104e+03 6.64392944e+02 1.11636194e+03 6.69948914e+02
    1.21526367e+03 6.74727600e+02 1.31404004e+03 6.79275208e+02
    1.41251892e+03 6.83575623e+02 6.15363403e+02 7.39789856e+02
    7.14554016e+02 7.45531067e+02 8.14284607e+02 7.50833069e+02
    9.14466553e+02 7.56519653e+02 1.01396167e+03 7.61732666e+02
    1.11338635e+03 7.66497803e+02 1.21327014e+03 7.71753540e+02
    1.31255701e+03 7.76368042e+02 1.41139514e+03 7.81067688e+02
    6.08611572e+02 8.37472900e+02 7.09081055e+02 8.43380737e+02
    8.08890808e+02 8.49153137e+02 9.10189209e+02 8.54454407e+02
    1.01021271e+03 8.59795959e+02 1.11061987e+03 8.64552185e+02
    1.21107751e+03 8.69229370e+02 1.31110925e+03 8.74184631e+02
    1.41063013e+03 8.78431152e+02 6.02185608e+02 9.37905945e+02
    7.03172729e+02 9.43653442e+02 8.03919922e+02 9.49336914e+02
    9.05647461e+02 9.54333557e+02 1.00677570e+03 9.59755554e+02
    1.10751208e+03 9.64568054e+02 1.20880762e+03 9.69650757e+02
    1.30959412e+03 9.73954895e+02 1.40970850e+03 9.78243958e+02
    5.95324463e+02 1.03841516e+03 6.97565369e+02 1.04397302e+03
    7.98954651e+02 1.04948743e+03 9.01472412e+02 1.05505420e+03
    1.00309253e+03 1.05973547e+03 1.10465271e+03 1.06479382e+03
    1.20642078e+03 1.06967712e+03 1.30802917e+03 1.07434412e+03
    1.40883130e+03 1.07813147e+03 5.88868713e+02 1.13978381e+03
    6.91557007e+02 1.14575037e+03 7.93657776e+02 1.15103113e+03
    8.97001221e+02 1.15665869e+03 9.99426208e+02 1.16182214e+03
    1.10179102e+03 1.16663098e+03 1.20431543e+03 1.17127246e+03
    1.30640259e+03 1.17555579e+03 1.40803406e+03 1.17962756e+03
    5.81690308e+02 8.34130920e+02 6.80847351e+02 8.42375488e+02
    7.79384888e+02 8.50350708e+02 8.79265991e+02 8.57742004e+02
    9.78194946e+02 8.65262390e+02 1.07724158e+03 8.72565613e+02
    1.17667957e+03 8.79314575e+02 1.27608423e+03 8.85628174e+02
    1.37514490e+03 8.91498108e+02 5.71754150e+02 9.25721375e+02
    6.71533997e+02 9.34042114e+02 7.71411377e+02 9.41729370e+02
    8.72070801e+02 9.49842651e+02 9.72150146e+02 9.57195862e+02
    1.07208142e+03 9.64058289e+02 1.17279810e+03 9.71321716e+02
    1.27295447e+03 9.77782532e+02 1.37281055e+03 9.84098389e+02
    5.61440796e+02 1.01818475e+03 6.62334412e+02 1.02678687e+03
    7.62873169e+02 1.03498059e+03 8.64789490e+02 1.04283411e+03
    9.65754761e+02 1.05028394e+03 1.06711462e+03 1.05725793e+03
    1.16858850e+03 1.06429443e+03 1.26972046e+03 1.07110095e+03
    1.37073218e+03 1.07734033e+03 5.50980042e+02 1.11358142e+03
    6.52903687e+02 1.12172461e+03 7.54537292e+02 1.13015417e+03
    8.57482544e+02 1.13790088e+03 9.59563904e+02 1.14567871e+03
    1.06166614e+03 1.15299487e+03 1.16446838e+03 1.16012732e+03
    1.26659521e+03 1.16676147e+03 1.36847559e+03 1.17323743e+03
    5.40405151e+02 1.20928809e+03 6.43520752e+02 1.21782495e+03
    7.46145935e+02 1.22613684e+03 8.50021667e+02 1.23407654e+03
    9.53127258e+02 1.24156982e+03 1.05631738e+03 1.24920740e+03
    1.15985352e+03 1.25639075e+03 1.26321533e+03 1.26330396e+03
    1.36596594e+03 1.26947070e+03 5.29497375e+02 1.30647009e+03
    6.33832092e+02 1.31544788e+03 7.37354126e+02 1.32416418e+03
    8.42389404e+02 1.33217297e+03 9.46565613e+02 1.33992700e+03
    1.05083130e+03 1.34739319e+03 1.15549817e+03 1.35451465e+03
    1.25970837e+03 1.36134802e+03 1.36364478e+03 1.36784424e+03
    8.59470154e+02 1.22992264e+02 9.54331177e+02 1.23687744e+02
    1.04841089e+03 1.24260109e+02 1.14359680e+03 1.25269325e+02
    1.23774915e+03 1.26184990e+02 1.33216809e+03 1.27497215e+02
    1.42645508e+03 1.29017273e+02 1.52082349e+03 1.30792465e+02
    1.61484692e+03 1.32787750e+02 8.59270325e+02 2.17588547e+02
    9.53252625e+02 2.17774139e+02 1.04696960e+03 2.18824295e+02
    1.14136609e+03 2.19501602e+02 1.23519238e+03 2.20492645e+02
    1.32872522e+03 2.21689941e+02 1.42278052e+03 2.23068268e+02
    1.51619116e+03 2.24649750e+02 1.60943750e+03 2.26415237e+02
    8.58885132e+02 3.10658813e+02 9.52308167e+02 3.11150726e+02
    1.04527856e+03 3.11606812e+02 1.13936658e+03 3.12456207e+02
    1.23240710e+03 3.13457581e+02 1.32552100e+03 3.14616699e+02
    1.41879321e+03 3.15814301e+02 1.51179553e+03 3.17206573e+02
    1.60429163e+03 3.18844360e+02 8.58527710e+02 4.03820160e+02
    9.51374084e+02 4.04067535e+02 1.04371606e+03 4.04831055e+02
    1.13719678e+03 4.05254974e+02 1.22968115e+03 4.06239716e+02
    1.32219385e+03 4.07125488e+02 1.41506226e+03 4.08574280e+02
    1.50730237e+03 4.09560150e+02 1.59922839e+03 4.11182739e+02
    8.58091431e+02 4.95293213e+02 9.50525452e+02 4.95595551e+02
    1.04232141e+03 4.95632721e+02 1.13501550e+03 4.96714294e+02
    1.22699780e+03 4.97319489e+02 1.31879187e+03 4.98192810e+02
    1.41094128e+03 4.99302795e+02 1.50264697e+03 5.00498047e+02
    1.59406116e+03 5.01720337e+02 8.57550415e+02 5.86112610e+02
    9.49374817e+02 5.85980164e+02 1.04063208e+03 5.86525696e+02
    1.13293872e+03 5.86967163e+02 1.22422925e+03 5.87785645e+02
    1.31559448e+03 5.88397339e+02 1.40702612e+03 5.89258850e+02
    1.49812231e+03 5.90531616e+02 1.58890930e+03 5.91601562e+02
    2.48683872e+01 1.37357056e+02 1.27399590e+02 1.39922348e+02
    2.29657883e+02 1.42352219e+02 3.32923828e+02 1.45000488e+02
    4.35661499e+02 1.47567078e+02 5.38779663e+02 1.50496353e+02
    6.42028076e+02 1.53483261e+02 7.45451721e+02 1.56481049e+02
    8.48725647e+02 1.59644272e+02 2.45732555e+01 2.43290146e+02
    1.26539299e+02 2.45548325e+02 2.28389236e+02 2.48294678e+02
    3.31375031e+02 2.50891342e+02 4.33971771e+02 2.53461777e+02
    5.36329895e+02 2.56225464e+02 6.39782837e+02 2.59252991e+02
    7.42542725e+02 2.62356110e+02 8.45368164e+02 2.65512054e+02
    2.39634686e+01 3.48027832e+02 1.25664230e+02 3.50574890e+02
    2.27174927e+02 3.53139038e+02 3.30067871e+02 3.55715057e+02
    4.31968262e+02 3.58418579e+02 5.34408569e+02 3.61272919e+02
    6.37209290e+02 3.64120239e+02 7.39757874e+02 3.67209412e+02
    8.42218506e+02 3.70302612e+02 2.36434441e+01 4.53451508e+02
    1.25031174e+02 4.55667633e+02 2.25974350e+02 4.58496521e+02
    3.28475616e+02 4.60878174e+02 4.30350647e+02 4.63728363e+02
    5.32194275e+02 4.66549896e+02 6.34987000e+02 4.69622223e+02
    7.36999695e+02 4.72241180e+02 8.38972473e+02 4.75534149e+02
    2.29670849e+01 5.57194946e+02 1.24434158e+02 5.59621399e+02
    2.25093826e+02 5.62008911e+02 3.27017853e+02 5.64801086e+02
    4.28433807e+02 5.67399719e+02 5.29969360e+02 5.70254639e+02
    6.32076477e+02 5.73107178e+02 7.34084839e+02 5.76177429e+02
    8.35915955e+02 5.79046631e+02 2.22521763e+01 6.60597717e+02
    1.23396500e+02 6.62921936e+02 2.23860703e+02 6.65662292e+02
    3.25474792e+02 6.68300110e+02 4.26606781e+02 6.71062561e+02
    5.27764709e+02 6.73712952e+02 6.29504028e+02 6.76391296e+02
    7.31173035e+02 6.79545166e+02 8.32485596e+02 6.82427002e+02
    6.27367249e+02 6.93928162e+02 7.19565918e+02 6.99831604e+02
    8.11429382e+02 7.05336182e+02 9.04363281e+02 7.10202393e+02
    9.96325806e+02 7.15456055e+02 1.08843591e+03 7.20187683e+02
    1.18081433e+03 7.24446655e+02 1.27310974e+03 7.28002502e+02
    1.36508105e+03 7.31104187e+02 6.20573120e+02 7.65670044e+02
    7.13774536e+02 7.71629150e+02 8.07065186e+02 7.76761292e+02
    9.00963318e+02 7.82637329e+02 9.94442139e+02 7.87320801e+02
    1.08756287e+03 7.91674927e+02 1.18137305e+03 7.96381348e+02
    1.27469299e+03 8.00330627e+02 1.36772571e+03 8.03921143e+02
    6.13363892e+02 8.38333740e+02 7.07994202e+02 8.44534058e+02
    8.02108276e+02 8.50321228e+02 8.97682495e+02 8.55657227e+02
    9.92186707e+02 8.60581848e+02 1.08697424e+03 8.64856873e+02
    1.18173340e+03 8.69345398e+02 1.27640393e+03 8.73567139e+02
    1.37055994e+03 8.77315308e+02 6.06137939e+02 9.13595703e+02
    7.01925415e+02 9.19530396e+02 7.97538330e+02 9.25436707e+02
    8.94243591e+02 9.30722046e+02 9.90239258e+02 9.35963318e+02
    1.08600110e+03 9.40780029e+02 1.18235889e+03 9.45223206e+02
    1.27818958e+03 9.49346863e+02 1.37370618e+03 9.53171692e+02
    5.98517090e+02 9.89501648e+02 6.96030457e+02 9.95689758e+02
    7.92855774e+02 1.00158832e+03 8.90819946e+02 1.00701282e+03
    9.88010559e+02 1.01194574e+03 1.08515735e+03 1.01714117e+03
    1.18263513e+03 1.02163947e+03 1.27991895e+03 1.02602551e+03
    1.37666296e+03 1.02961951e+03 5.90974670e+02 1.06660730e+03
    6.89665405e+02 1.07346741e+03 7.87753601e+02 1.07968335e+03
    8.87213379e+02 1.08536792e+03 9.85751465e+02 1.09057605e+03
    1.08435437e+03 1.09557349e+03 1.18325256e+03 1.10022705e+03
    1.28172473e+03 1.10447974e+03 1.37976489e+03 1.10826355e+03
    6.27367126e+02 6.94269226e+02 7.19641724e+02 7.00176208e+02
    8.11498901e+02 7.05627563e+02 9.04406799e+02 7.10501831e+02
    9.96362061e+02 7.15747070e+02 1.08846582e+03 7.20619019e+02
    1.18078894e+03 7.24711548e+02 1.27311780e+03 7.28383484e+02
    1.36505493e+03 7.31394104e+02 6.20606873e+02 7.65997009e+02
    7.13802856e+02 7.71912415e+02 8.07089050e+02 7.77117554e+02
    9.00958252e+02 7.82859314e+02 9.94442688e+02 7.87592163e+02
    1.08756494e+03 7.92067261e+02 1.18141040e+03 7.96662476e+02
    1.27464734e+03 8.00584412e+02 1.36775537e+03 8.04282471e+02
    6.13402100e+02 8.38519958e+02 7.07993469e+02 8.44769897e+02
    8.02161316e+02 8.50504761e+02 8.97692871e+02 8.55944458e+02
    9.92130737e+02 8.60754272e+02 1.08699927e+03 8.65177612e+02
    1.18174536e+03 8.69578735e+02 1.27641504e+03 8.73792847e+02
    1.37054126e+03 8.77614502e+02 6.06149170e+02 9.13721924e+02
    7.01933167e+02 9.19663635e+02 7.97489685e+02 9.25565002e+02
    8.94247925e+02 9.30901062e+02 9.90213135e+02 9.36161682e+02
    1.08598669e+03 9.40894043e+02 1.18236536e+03 9.45427795e+02
    1.27817944e+03 9.49538330e+02 1.37362988e+03 9.53379883e+02
    5.98572937e+02 9.89474243e+02 6.95969543e+02 9.95725952e+02
    7.92831787e+02 1.00171149e+03 8.90824280e+02 1.00715710e+03
    9.87955750e+02 1.01206940e+03 1.08508105e+03 1.01725623e+03
    1.18259875e+03 1.02181702e+03 1.27982422e+03 1.02621826e+03
    1.37662292e+03 1.02982861e+03 5.90906555e+02 1.06658240e+03
    6.89638794e+02 1.07344324e+03 7.87719604e+02 1.07967761e+03
    8.87231140e+02 1.08533240e+03 9.85727966e+02 1.09067175e+03
    1.08431860e+03 1.09566809e+03 1.18320972e+03 1.10032275e+03
    1.28166321e+03 1.10458081e+03 1.37969482e+03 1.10841614e+03
    6.27384155e+02 6.94328613e+02 7.19617065e+02 7.00328674e+02
    8.11492310e+02 7.05744934e+02 9.04419922e+02 7.10630615e+02
    9.96377563e+02 7.15863403e+02 1.08849231e+03 7.20660156e+02
    1.18084937e+03 7.24831299e+02 1.27316296e+03 7.28479553e+02
    1.36508630e+03 7.31534302e+02 6.20593689e+02 7.66075623e+02
    7.13876831e+02 7.72035522e+02 8.07122070e+02 7.77218994e+02
    9.00963501e+02 7.82943909e+02 9.94458984e+02 7.87678040e+02
    1.08762866e+03 7.92195129e+02 1.18146191e+03 7.96771606e+02
    1.27468921e+03 8.00734009e+02 1.36774646e+03 8.04354492e+02
    6.13406250e+02 8.38614868e+02 7.08004639e+02 8.44826416e+02
    8.02176086e+02 8.50620605e+02 8.97699768e+02 8.56027893e+02
    9.92184448e+02 8.60829285e+02 1.08697119e+03 8.65221680e+02
    1.18176404e+03 8.69677979e+02 1.27643799e+03 8.73965088e+02
    1.37061743e+03 8.77716431e+02 6.06121460e+02 9.13826416e+02
    7.01987488e+02 9.19800354e+02 7.97593567e+02 9.25617493e+02
    8.94217896e+02 9.30970337e+02 9.90247925e+02 9.36217163e+02
    1.08602051e+03 9.41000061e+02 1.18239648e+03 9.45514221e+02
    1.27819104e+03 9.49665833e+02 1.37373291e+03 9.53484497e+02
    5.98619629e+02 9.89538086e+02 6.96055908e+02 9.95789246e+02
    7.92874207e+02 1.00178394e+03 8.90826538e+02 1.00724359e+03
    9.87950500e+02 1.01221539e+03 1.08515698e+03 1.01734918e+03
    1.18262842e+03 1.02190302e+03 1.27988574e+03 1.02634631e+03
    1.37662744e+03 1.02993433e+03 5.90938599e+02 1.06664148e+03
    6.89628967e+02 1.07353601e+03 7.87731812e+02 1.07978210e+03
    8.87241089e+02 1.08547021e+03 9.85711365e+02 1.09073303e+03
    1.08438562e+03 1.09573523e+03 1.18321606e+03 1.10040295e+03
    1.28171423e+03 1.10464026e+03 1.37977295e+03 1.10848999e+03
    6.27433350e+02 6.94342651e+02 7.19644958e+02 7.00305359e+02
    8.11527161e+02 7.05806152e+02 9.04394287e+02 7.10631897e+02
    9.96385376e+02 7.15902466e+02 1.08847742e+03 7.20673096e+02
    1.18089490e+03 7.24838318e+02 1.27323474e+03 7.28473938e+02
    1.36502246e+03 7.31491516e+02 6.20679504e+02 7.66054504e+02
    7.13868713e+02 7.72052917e+02 8.07111877e+02 7.77240356e+02
    9.01038635e+02 7.82976562e+02 9.94471008e+02 7.87670593e+02
    1.08757227e+03 7.92186523e+02 1.18146851e+03 7.96767578e+02
    1.27465161e+03 8.00640442e+02 1.36775623e+03 8.04328308e+02
    6.13450378e+02 8.38585632e+02 7.08098877e+02 8.44860657e+02
    8.02201233e+02 8.50652405e+02 8.97728149e+02 8.56033813e+02
    9.92154236e+02 8.60826599e+02 1.08696436e+03 8.65204712e+02
    1.18180469e+03 8.69702393e+02 1.27638489e+03 8.73870789e+02
    1.37058496e+03 8.77699219e+02 6.06127319e+02 9.13783142e+02
    7.02020752e+02 9.19829468e+02 7.97608704e+02 9.25637451e+02
    8.94271179e+02 9.31008850e+02 9.90281677e+02 9.36265503e+02
    1.08604358e+03 9.41002869e+02 1.18236780e+03 9.45532288e+02
    1.27819751e+03 9.49645264e+02 1.37369092e+03 9.53448486e+02
    5.98648682e+02 9.89568726e+02 6.96065491e+02 9.95776306e+02
    7.92855652e+02 1.00176154e+03 8.90859741e+02 1.00722565e+03
    9.88023438e+02 1.01217352e+03 1.08516248e+03 1.01733881e+03
    1.18266821e+03 1.02187592e+03 1.27991821e+03 1.02634302e+03
    1.37664929e+03 1.02989124e+03 5.90981018e+02 1.06664111e+03
    6.89676514e+02 1.07352441e+03 7.87749817e+02 1.07973572e+03
    8.87266296e+02 1.08546790e+03 9.85725342e+02 1.09069446e+03
    1.08440369e+03 1.09576843e+03 1.18323535e+03 1.10038733e+03
    1.28171289e+03 1.10465149e+03 1.37979553e+03 1.10843188e+03
    6.27394836e+02 6.94317078e+02 7.19687134e+02 7.00237732e+02
    8.11484375e+02 7.05766663e+02 9.04407532e+02 7.10590210e+02
    9.96419189e+02 7.15879456e+02 1.08849927e+03 7.20626526e+02
    1.18086377e+03 7.24759216e+02 1.27317737e+03 7.28404602e+02
    1.36512512e+03 7.31441956e+02 6.20631775e+02 7.66045654e+02
    7.13947021e+02 7.72018494e+02 8.07150635e+02 7.77202759e+02
    9.01001709e+02 7.82964600e+02 9.94457886e+02 7.87632324e+02
    1.08764563e+03 7.92137512e+02 1.18144385e+03 7.96745117e+02
    1.27470410e+03 8.00662415e+02 1.36778760e+03 8.04341736e+02
    6.13477600e+02 8.38630981e+02 7.08113525e+02 8.44806396e+02
    8.02232422e+02 8.50620056e+02 8.97774536e+02 8.56017212e+02
    9.92190857e+02 8.60792114e+02 1.08705237e+03 8.65188049e+02
    1.18182642e+03 8.69685486e+02 1.27645972e+03 8.73804810e+02
    1.37064929e+03 8.77654175e+02 6.06158813e+02 9.13802490e+02
    7.02048767e+02 9.19719360e+02 7.97599609e+02 9.25625183e+02
    8.94280334e+02 9.30972534e+02 9.90279541e+02 9.36260071e+02
    1.08606372e+03 9.40981995e+02 1.18244141e+03 9.45478760e+02
    1.27822205e+03 9.49632324e+02 1.37370129e+03 9.53437256e+02
    5.98648010e+02 9.89549316e+02 6.96100464e+02 9.95813354e+02
    7.92908508e+02 1.00175903e+03 8.90835388e+02 1.00721210e+03
    9.88086792e+02 1.01212909e+03 1.08517493e+03 1.01734253e+03
    1.18268213e+03 1.02187195e+03 1.27997205e+03 1.02633069e+03
    1.37671606e+03 1.02986499e+03 5.90968201e+02 1.06659387e+03
    6.89692993e+02 1.07348120e+03 7.87761963e+02 1.07969910e+03
    8.87290588e+02 1.08541467e+03 9.85802063e+02 1.09071057e+03
    1.08440979e+03 1.09574780e+03 1.18328979e+03 1.10036536e+03
    1.28176721e+03 1.10460376e+03 1.37980579e+03 1.10844788e+03</data></image_points>
</opencv_storage>
